{"matchInfo":{"id":"2zrdrffa15bo2uaz61g345gfe","coverageLevel":"8","date":"2019-05-18Z","time":"22:00:00Z","week":"13","lastUpdated":"2020-02-18T00:28:32Z","description":"Puerto Montt vs Deportes Temuco","sport":{"id":"289u5typ3vp4ifwh5thalohmq","name":"Soccer"},"ruleset":{"id":"79plas4983031idr6vw83nuel","name":"Men"},"competition":{"id":"bly7ema5au6j40i0grhl0pnub","name":"Primera B","competitionCode":"PRB","competitionFormat":"Domestic league","country":{"id":"32tb8d7824xg4i0ybxzssczu0","name":"Chile"}},"tournamentCalendar":{"id":"2owzodd8n4cvwnl36264jo50q","startDate":"2019-02-16Z","endDate":"2020-01-24Z","name":"2019"},"stage":{"id":"2pr11uska0n5co3b22z7crvxm","formatId":"e2q01r9o9jwiq1fls93d1sslx","startDate":"2019-02-16Z","endDate":"2019-12-08Z","name":"Regular Season"},"contestant":[{"id":"c79dztwjlrdn268fzce3ssuzz","name":"Puerto Montt","shortName":"Puerto Montt","officialName":"CD Puerto Montt","code":"PMO","position":"home","country":{"id":"32tb8d7824xg4i0ybxzssczu0","name":"Chile"}},{"id":"3offzg5j5vzqmrra2lx73kbu7","name":"Deportes Temuco","shortName":"Temuco","officialName":"CD Temuco","code":"TEM","position":"away","country":{"id":"32tb8d7824xg4i0ybxzssczu0","name":"Chile"}}],"venue":{"id":"atk63hxxmv23rdh6thmcv9vf4","neutral":"no","longName":"Estadio Bicentenario de Chinquihue","shortName":"Estadio Bicentenario de Chinquihue"}},"liveData":{"matchDetails":{"periodId":14,"matchStatus":"Played","winner":"home","matchLengthMin":96,"matchLengthSec":54,"period":[{"id":1,"start":"2019-05-18T21:59:18Z","end":"2019-05-18T22:45:32Z","lengthMin":46,"lengthSec":14},{"id":2,"start":"2019-05-18T23:01:56Z","end":"2019-05-18T23:52:36Z","lengthMin":50,"lengthSec":40}],"scores":{"ht":{"home":1,"away":0},"ft":{"home":2,"away":1},"total":{"home":2,"away":1}}},"goal":[{"contestantId":"c79dztwjlrdn268fzce3ssuzz","periodId":1,"timeMin":31,"timeMinSec":"30:59","lastUpdated":"2019-05-18T22:31:19Z","type":"G","scorerId":"1ips6o8k8ujsuo29uswpac2c5","scorerName":"I. Lemmo","optaEventId":"1888897009","homeScore":1,"awayScore":0},{"contestantId":"3offzg5j5vzqmrra2lx73kbu7","periodId":2,"timeMin":82,"timeMinSec":"82:00","lastUpdated":"2019-05-18T23:39:20Z","type":"G","scorerId":"cn9hx4byy5adg51wu4txij4r9","scorerName":"L. Casanova","optaEventId":"711540449","homeScore":1,"awayScore":1},{"contestantId":"c79dztwjlrdn268fzce3ssuzz","periodId":2,"timeMin":95,"timeMinSec":"94:34","lastUpdated":"2019-05-18T23:52:45Z","type":"G","scorerId":"9qzfichl4hqzv5vwyp3bo8vdh","scorerName":"N. Gauna","optaEventId":"1916103973","homeScore":2,"awayScore":1}],"card":[{"contestantId":"c79dztwjlrdn268fzce3ssuzz","periodId":1,"timeMin":33,"timeMinSec":"32:39","lastUpdated":"2019-05-18T22:32:44Z","type":"YC","playerId":"7aqz61y3e65gjsbcgn2qradat","playerName":"R. Barroilhet","optaEventId":"690081496","cardReason":"Foul"},{"contestantId":"3offzg5j5vzqmrra2lx73kbu7","periodId":1,"timeMin":36,"timeMinSec":"35:53","lastUpdated":"2019-05-18T22:39:59Z","type":"YC","playerId":"9jkjgro1da0kr5015yrwgqw2d","playerName":"S. Dominguez","optaEventId":"1009687372","cardReason":"Foul"},{"contestantId":"3offzg5j5vzqmrra2lx73kbu7","periodId":2,"timeMin":72,"timeMinSec":"71:45","lastUpdated":"2019-05-18T23:28:59Z","type":"RC","playerId":"ce7x4wgl9lwdnz1t248euc0r9","playerName":"A. Ábalos","optaEventId":"1378708509","cardReason":"Foul"},{"contestantId":"3offzg5j5vzqmrra2lx73kbu7","periodId":2,"timeMin":76,"timeMinSec":"75:18","lastUpdated":"2019-05-18T23:32:19Z","type":"YC","playerId":"dg9dpni3v7c5j8s9eke5tan6d","playerName":"J. Fuentes","optaEventId":"146071463","cardReason":"Foul"},{"contestantId":"c79dztwjlrdn268fzce3ssuzz","periodId":2,"timeMin":77,"timeMinSec":"76:34","lastUpdated":"2019-05-18T23:34:09Z","type":"RC","playerId":"d6vvbkwsg3rluvpmif4i4rvmd","playerName":"J. Aquino","optaEventId":"986505158","cardReason":"Foul"},{"contestantId":"3offzg5j5vzqmrra2lx73kbu7","periodId":2,"timeMin":77,"timeMinSec":"77:00","lastUpdated":"2019-05-18T23:35:16Z","type":"YC","playerId":"1745kyfnv6qp9ff0xxzju67dh","playerName":"B. Taiva","optaEventId":"540892907","cardReason":"Foul"},{"contestantId":"3offzg5j5vzqmrra2lx73kbu7","periodId":2,"timeMin":90,"timeMinSec":"89:34","lastUpdated":"2019-05-18T23:46:34Z","type":"YC","playerId":"cn9hx4byy5adg51wu4txij4r9","playerName":"L. Casanova","optaEventId":"753661576","cardReason":"Foul"}],"substitute":[{"contestantId":"3offzg5j5vzqmrra2lx73kbu7","periodId":2,"timeMin":46,"timeMinSec":"45:00","lastUpdated":"2019-05-18T23:05:25Z","playerOnId":"1z1b10urbis9b1s5325k37k5x","playerOnName":"R. Cepeda","playerOffId":"95tcq7lp8007cb4jqquax9vu2","playerOffName":"C. Zamorano","subReason":"Tactical"},{"contestantId":"3offzg5j5vzqmrra2lx73kbu7","periodId":2,"timeMin":60,"timeMinSec":"60:00","lastUpdated":"2019-05-18T23:18:09Z","playerOnId":"dg9dpni3v7c5j8s9eke5tan6d","playerOnName":"J. Fuentes","playerOffId":"bpdlrit65tqt649ro5rtipd5h","playerOffName":"B. Viveros","subReason":"Tactical"},{"contestantId":"c79dztwjlrdn268fzce3ssuzz","periodId":2,"timeMin":74,"timeMinSec":"73:40","lastUpdated":"2019-05-18T23:30:45Z","playerOnId":"8r0u6b30z73l3uwhyv5zbpotl","playerOnName":"N. Servetto","playerOffId":"7aqz61y3e65gjsbcgn2qradat","playerOffName":"R. Barroilhet","subReason":"Tactical"},{"contestantId":"c79dztwjlrdn268fzce3ssuzz","periodId":2,"timeMin":79,"timeMinSec":"78:23","lastUpdated":"2019-05-18T23:36:44Z","playerOnId":"20c926dqjaejgqrx4v04n2ort","playerOnName":"A. Rodríguez","playerOffId":"21yxomlpwzh54k7tivw3j457u","playerOffName":"A. Souper","subReason":"Tactical"},{"contestantId":"3offzg5j5vzqmrra2lx73kbu7","periodId":2,"timeMin":79,"timeMinSec":"78:51","lastUpdated":"2019-05-18T23:36:44Z","playerOnId":"2uwrwkd5fkuro3hv5wbyxm0gl","playerOnName":"R. Quiñónes","playerOffId":"9jkjgro1da0kr5015yrwgqw2d","playerOffName":"S. Dominguez","subReason":"Tactical"}],"lineUp":[{"contestantId":"c79dztwjlrdn268fzce3ssuzz","player":[{"playerId":"3tm64gd7gj7qjmdt8ml3d9t5h","firstName":"Gino Paolo","lastName":"Alucema Dinamarca","matchName":"G. Alucema","stat":[{"type":"goalsConceded","value":"1"},{"type":"gameStarted","value":"1"},{"type":"minsPlayed","value":"90"},{"type":"formationPlace","value":"3"}]},{"playerId":"d6vvbkwsg3rluvpmif4i4rvmd","firstName":"Jorge Daniel","lastName":"Aquino Guerrero","matchName":"J. Aquino","stat":[{"type":"redCard","value":"1"},{"type":"gameStarted","value":"1"},{"type":"minsPlayed","value":"77"},{"type":"formationPlace","value":"2"}]},{"playerId":"7aqz61y3e65gjsbcgn2qradat","firstName":"Richard","lastName":"Barroilhet","matchName":"R. Barroilhet","stat":[{"type":"yellowCard","value":"1"},{"type":"totalSubOff","value":"1"},{"type":"gameStarted","value":"1"},{"type":"minsPlayed","value":"74"},{"type":"formationPlace","value":"4"}]},{"playerId":"5rroezi2jpvsodccnji9pvd2h","firstName":"Bayron","lastName":"Bustamante Gamboa","matchName":"B. Bustamante","stat":[{"type":"goalsConceded","value":"1"},{"type":"gameStarted","value":"1"},{"type":"minsPlayed","value":"90"},{"type":"formationPlace","value":"5"}]},{"playerId":"b4j56svj3r32qon5qh0wp0lat","firstName":"Daniel","lastName":"Castillo","matchName":"D. Castillo","stat":[{"type":"goalsConceded","value":"1"},{"type":"gameStarted","value":"1"},{"type":"minsPlayed","value":"90"},{"type":"formationPlace","value":"1"}]},{"playerId":"huvdnx1gqfx8yhr50nhmowk5","firstName":"Fernando Esteban","lastName":"Cornejo Padilla","matchName":"F. Cornejo","stat":[{"type":"goalsConceded","value":"1"},{"type":"gameStarted","value":"1"},{"type":"minsPlayed","value":"90"},{"type":"formationPlace","value":"6"}]},{"playerId":"9qzfichl4hqzv5vwyp3bo8vdh","firstName":"Nicolás Arturo","lastName":"Gauna","matchName":"N. Gauna","stat":[{"type":"goalsConceded","value":"1"},{"type":"ontargetScoringAtt","value":"1"},{"type":"totalScoringAtt","value":"1"},{"type":"goals","value":"1"},{"type":"gameStarted","value":"1"},{"type":"minsPlayed","value":"90"},{"type":"formationPlace","value":"7"}]},{"playerId":"39bxq8h3f1sd6rx8vktcmonv9","firstName":"Orlando Salvador","lastName":"Gutierrez Leiva","matchName":"O. Gutierrez","stat":[{"type":"goalsConceded","value":"1"},{"type":"gameStarted","value":"1"},{"type":"minsPlayed","value":"90"},{"type":"formationPlace","value":"8"}]},{"playerId":"1ips6o8k8ujsuo29uswpac2c5","firstName":"Ignacio Nicolás","lastName":"Lemmo Gervasio","matchName":"I. Lemmo","stat":[{"type":"goalsConceded","value":"1"},{"type":"ontargetScoringAtt","value":"1"},{"type":"totalScoringAtt","value":"1"},{"type":"goals","value":"1"},{"type":"gameStarted","value":"1"},{"type":"minsPlayed","value":"90"},{"type":"formationPlace","value":"9"}]},{"playerId":"ew81y54i390wxgdm0bpjhf1zp","firstName":"Gonzalo Alfredo","lastName":"Sepúlveda Domínguez","matchName":"G. Sepúlveda","stat":[{"type":"goalsConceded","value":"1"},{"type":"gameStarted","value":"1"},{"type":"minsPlayed","value":"90"},{"type":"formationPlace","value":"10"}]},{"playerId":"21yxomlpwzh54k7tivw3j457u","firstName":"Andrés","lastName":"Souper De La Cruz","matchName":"A. Souper","stat":[{"type":"totalSubOff","value":"1"},{"type":"gameStarted","value":"1"},{"type":"minsPlayed","value":"79"},{"type":"formationPlace","value":"11"}]},{"playerId":"1tfpt337ci3j2v3oxpo3w4clx","firstName":"Braulio Esteban","lastName":"Baeza Figueroa","matchName":"B. Baeza","position":"Substitute","stat":[{"type":"formationPlace","value":"0"}]},{"playerId":"b2i6d0raikry156g7qgtt7dre","firstName":"Ignacio Esteban","lastName":"Castillo Barria","matchName":"I. Castillo","position":"Substitute","stat":[{"type":"formationPlace","value":"0"}]},{"playerId":"d852vrwmsyj3ck3b6hi08u6l1","firstName":"Octavio Ernesto","lastName":"Pozo Miranda","matchName":"O. Pozo","position":"Substitute","stat":[{"type":"formationPlace","value":"0"}]},{"playerId":"4ze29xoiozjl1h2iwwejpxvx1","firstName":"Jonathan Eduardo","lastName":"Rebolledo Ardiles","matchName":"J. Rebolledo","position":"Substitute","stat":[{"type":"formationPlace","value":"0"}]},{"playerId":"20c926dqjaejgqrx4v04n2ort","firstName":"Alonso Andrés","lastName":"Rodríguez Rojas","matchName":"A. Rodríguez","position":"Substitute","stat":[{"type":"goalsConceded","value":"1"},{"type":"totalSubOn","value":"1"},{"type":"minsPlayed","value":"11"},{"type":"formationPlace","value":"0"}]},{"playerId":"8r0u6b30z73l3uwhyv5zbpotl","firstName":"Nicolás","lastName":"Servetto","matchName":"N. Servetto","position":"Substitute","stat":[{"type":"goalsConceded","value":"1"},{"type":"totalSubOn","value":"1"},{"type":"minsPlayed","value":"16"},{"type":"formationPlace","value":"0"}]},{"playerId":"31z90djiddm6fkeszcis06i21","firstName":"Diego","lastName":"Subiabre Silva","matchName":"D. Subiabre","position":"Substitute","stat":[{"type":"formationPlace","value":"0"}]}],"teamOfficial":{"id":"4olmshzla37l0cur1jn3tc05x","firstName":"Luis Fernando","lastName":"Vergara Meylan","type":"manager"},"stat":[{"fh":"0","sh":"1","type":"goalsConceded","value":"1"},{"fh":"1","sh":"1","type":"ontargetScoringAtt","value":"2"},{"fh":"1","sh":"1","type":"totalScoringAtt","value":"2"},{"fh":"0","sh":"2","type":"subsMade","value":"2"},{"fh":"1","sh":"0","type":"totalYellowCard","value":"1"},{"fh":"0","sh":"1","type":"totalRedCard","value":"1"},{"fh":"1","sh":"1","type":"goals","value":"2"},{"type":"formationUsed","value":""}]},{"contestantId":"3offzg5j5vzqmrra2lx73kbu7","player":[{"playerId":"2zm1xbpwuruyv0p7abik1ub4l","firstName":"Joaquín","lastName":"Aros Melgarejo","matchName":"J. Aros","stat":[{"type":"goalsConceded","value":"2"},{"type":"gameStarted","value":"1"},{"type":"minsPlayed","value":"90"},{"type":"formationPlace","value":"9"}]},{"playerId":"cn9hx4byy5adg51wu4txij4r9","firstName":"Luis Ignacio","lastName":"Casanova Sandoval","matchName":"L. Casanova","stat":[{"type":"yellowCard","value":"1"},{"type":"goalsConceded","value":"2"},{"type":"ontargetScoringAtt","value":"1"},{"type":"totalScoringAtt","value":"1"},{"type":"goals","value":"1"},{"type":"gameStarted","value":"1"},{"type":"minsPlayed","value":"90"},{"type":"formationPlace","value":"3"}]},{"playerId":"3936uvdkxl4lzafpkxi8fcauh","firstName":"Reiner Alvey","lastName":"Castro Barrera","matchName":"R. Castro","stat":[{"type":"goalsConceded","value":"2"},{"type":"gameStarted","value":"1"},{"type":"minsPlayed","value":"90"},{"type":"formationPlace","value":"6"}]},{"playerId":"abngq8zx2pm9ho44rs7830mhh","firstName":"Matías Ezequiel","lastName":"Di Benedetto","matchName":"M. Di Benedetto","stat":[{"type":"goalsConceded","value":"2"},{"type":"gameStarted","value":"1"},{"type":"minsPlayed","value":"90"},{"type":"formationPlace","value":"8"}]},{"playerId":"9jkjgro1da0kr5015yrwgqw2d","firstName":"Sebastian","lastName":"Dominguez Montero","matchName":"S. Dominguez","stat":[{"type":"yellowCard","value":"1"},{"type":"goalsConceded","value":"1"},{"type":"totalSubOff","value":"1"},{"type":"gameStarted","value":"1"},{"type":"minsPlayed","value":"79"},{"type":"formationPlace","value":"2"}]},{"playerId":"9lrkn9hedic9ljenq1dbqk9ud","firstName":"Guillermo","lastName":"Díaz Ayala","matchName":"G. Díaz","stat":[{"type":"goalsConceded","value":"2"},{"type":"gameStarted","value":"1"},{"type":"minsPlayed","value":"90"},{"type":"formationPlace","value":"5"}]},{"playerId":"b576admrgqmlyrobr6r5n01xx","firstName":"Jose Luis","lastName":"Gamonal Ruiz","matchName":"J. Gamonal","stat":[{"type":"goalsConceded","value":"2"},{"type":"gameStarted","value":"1"},{"type":"minsPlayed","value":"90"},{"type":"formationPlace","value":"1"}]},{"playerId":"1745kyfnv6qp9ff0xxzju67dh","firstName":"Bryan","lastName":"Taiva Lobos","matchName":"B. Taiva","stat":[{"type":"yellowCard","value":"1"},{"type":"goalsConceded","value":"2"},{"type":"gameStarted","value":"1"},{"type":"minsPlayed","value":"90"},{"type":"formationPlace","value":"4"}]},{"playerId":"bpdlrit65tqt649ro5rtipd5h","firstName":"Brayams Marcelo","lastName":"Viveros Alvarado","matchName":"B. Viveros","stat":[{"type":"goalsConceded","value":"1"},{"type":"totalSubOff","value":"1"},{"type":"gameStarted","value":"1"},{"type":"minsPlayed","value":"60"},{"type":"formationPlace","value":"7"}]},{"playerId":"95tcq7lp8007cb4jqquax9vu2","firstName":"Claudio Ignacio","lastName":"Zamorano Salamanca","matchName":"C. Zamorano","stat":[{"type":"goalsConceded","value":"1"},{"type":"totalSubOff","value":"1"},{"type":"gameStarted","value":"1"},{"type":"minsPlayed","value":"45"},{"type":"formationPlace","value":"11"}]},{"playerId":"ce7x4wgl9lwdnz1t248euc0r9","firstName":"Alfredo Omar","lastName":"Ábalos","matchName":"A. Ábalos","stat":[{"type":"goalsConceded","value":"1"},{"type":"redCard","value":"1"},{"type":"gameStarted","value":"1"},{"type":"minsPlayed","value":"72"},{"type":"formationPlace","value":"10"}]},{"playerId":"1zjs40vg8awcxd7cn72hmsi51","firstName":"Yerko Mauricio","lastName":"Aguila Bastías","matchName":"Y. Aguila","position":"Substitute","stat":[{"type":"formationPlace","value":"0"}]},{"playerId":"6ovldi22wgo63w8ezraxo45t6","firstName":"Diego","lastName":"Arias","matchName":"D. Arias","position":"Substitute","stat":[{"type":"formationPlace","value":"0"}]},{"playerId":"1z1b10urbis9b1s5325k37k5x","firstName":"Ruben","lastName":"Cepeda","matchName":"R. Cepeda","position":"Substitute","stat":[{"type":"goalsConceded","value":"1"},{"type":"totalSubOn","value":"1"},{"type":"minsPlayed","value":"45"},{"type":"formationPlace","value":"0"}]},{"playerId":"dg9dpni3v7c5j8s9eke5tan6d","firstName":"Johan Patricio","lastName":"Fuentes Muñoz","matchName":"J. Fuentes","position":"Substitute","stat":[{"type":"yellowCard","value":"1"},{"type":"goalsConceded","value":"1"},{"type":"totalSubOn","value":"1"},{"type":"minsPlayed","value":"30"},{"type":"formationPlace","value":"0"}]},{"playerId":"8poy0shq17ruyrbk64uolzqad","firstName":"Guillermo Enrique","lastName":"Orellana Riquelme","matchName":"G. Orellana","position":"Substitute","stat":[{"type":"formationPlace","value":"0"}]},{"playerId":"2uwrwkd5fkuro3hv5wbyxm0gl","firstName":"Rodin Jair","lastName":"Quiñónes Rentería","matchName":"R. Quiñónes","position":"Substitute","stat":[{"type":"goalsConceded","value":"1"},{"type":"totalSubOn","value":"1"},{"type":"minsPlayed","value":"11"},{"type":"formationPlace","value":"0"}]},{"playerId":"a6pbq7r6cktnf7s0tlkm08ul1","firstName":"Cristóbal Alberto","lastName":"Vergara Maldonado","matchName":"C. Vergara","position":"Substitute","stat":[{"type":"formationPlace","value":"0"}]}],"teamOfficial":{"id":"5u2guimjmaj88o4z1ly8ynw7p","firstName":"Hugo Alejandro Héctor","lastName":"Vilches Manuguian","type":"manager"},"stat":[{"fh":"1","sh":"1","type":"goalsConceded","value":"2"},{"fh":"0","sh":"1","type":"ontargetScoringAtt","value":"1"},{"fh":"0","sh":"1","type":"totalScoringAtt","value":"1"},{"fh":"0","sh":"3","type":"subsMade","value":"3"},{"fh":"1","sh":"3","type":"totalYellowCard","value":"4"},{"fh":"0","sh":"1","type":"totalRedCard","value":"1"},{"fh":"0","sh":"1","type":"goals","value":"1"},{"type":"formationUsed","value":""}]}],"matchDetailsExtra":{"attendance":"4402","matchOfficial":[{"id":"8k4mjxysjcwppmkgf3w3yyfsa","type":"Main","firstName":"Rodrigo","lastName":"Carvajal"}]}}}