{"matchInfo":{"id":"civfhdbycxxmwn8h627qrqooa","coverageLevel":"3","date":"2018-05-06Z","time":"20:00:00Z","lastUpdated":"2020-02-06T16:18:47Z","description":"San Marcos vs Deportes Vallenar","sport":{"id":"289u5typ3vp4ifwh5thalohmq","name":"Soccer"},"ruleset":{"id":"79plas4983031idr6vw83nuel","name":"Men"},"competition":{"id":"eu2g5j36zzxiazpd729osx0wm","name":"Copa Chile","competitionCode":"COC","competitionFormat":"Domestic cup","country":{"id":"32tb8d7824xg4i0ybxzssczu0","name":"Chile"}},"tournamentCalendar":{"id":"atdps5tkmtv0lqa5do2geu1re","startDate":"2018-04-25Z","endDate":"2018-11-18Z","name":"2018"},"stage":{"id":"atzegg9czplfqvni7kpdmcfai","formatId":"3ad6z07rilk8flizkw1bhv179","startDate":"2018-04-25Z","endDate":"2018-05-17Z","name":"1st Round"},"contestant":[{"id":"a6g25i52b5wrzwn7xb5g9u266","name":"San Marcos","shortName":"San Marcos","officialName":"CD San Marcos de Arica","code":"SMA","position":"home","country":{"id":"32tb8d7824xg4i0ybxzssczu0","name":"Chile"}},{"id":"26j8jh3je1ghdwsqxsbmre8d1","name":"Deportes Vallenar","shortName":"Vallenar","officialName":"Club de Deportes Vallenar","code":"VAL","position":"away","country":{"id":"32tb8d7824xg4i0ybxzssczu0","name":"Chile"}}],"venue":{"id":"esatb0cwtnfw0z2k1okkmc771","neutral":"no","longName":"Estadio Carlos Dittborn","shortName":"Estadio Carlos Dittborn"}},"liveData":{"matchDetails":{"periodId":14,"matchStatus":"Played","winner":"draw","relatedMatchId":"dmp5ur5z8mjgg6p6tlew39x0q","aggregateWinnerId":"a6g25i52b5wrzwn7xb5g9u266","scores":{"ht":{"home":1,"away":1},"ft":{"home":1,"away":1},"total":{"home":1,"away":1},"aggregate":{"home":3,"away":1}}},"goal":[{"contestantId":"a6g25i52b5wrzwn7xb5g9u266","periodId":1,"timeMin":19,"lastUpdated":"2018-05-08T17:23:38Z","type":"G","scorerId":"dx5urw0sc59agxirgzd77u4et","scorerName":"M. Sánchez","homeScore":1,"awayScore":0},{"contestantId":"26j8jh3je1ghdwsqxsbmre8d1","periodId":1,"timeMin":26,"lastUpdated":"2018-05-08T17:23:42Z","type":"G","scorerId":"6qer5dufqvyq4wwi9wxb4muol","scorerName":"D. Cuéllar","homeScore":1,"awayScore":1}],"card":[{"contestantId":"a6g25i52b5wrzwn7xb5g9u266","periodId":1,"timeMin":20,"lastUpdated":"2019-10-12T23:22:13Z","type":"YC","playerId":"16khuyqiy8jr8lhbf1fr2xxat","playerName":"M. González","cardReason":"Foul"},{"contestantId":"26j8jh3je1ghdwsqxsbmre8d1","periodId":1,"timeMin":33,"lastUpdated":"2019-10-12T23:20:38Z","type":"YC","playerId":"43krx180jhca256jl3lnzbcut","playerName":"F. Herrera","cardReason":"Foul"},{"contestantId":"26j8jh3je1ghdwsqxsbmre8d1","periodId":2,"timeMin":77,"lastUpdated":"2019-10-12T23:20:44Z","type":"YC","playerId":"2s76t15xvjmcodt3tlkw9zg0l","playerName":"J. Lopez","cardReason":"Foul"}],"substitute":[{"contestantId":"26j8jh3je1ghdwsqxsbmre8d1","periodId":2,"timeMin":46,"lastUpdated":"2019-10-12T23:20:48Z","playerOnId":"dyrbtgl17trirrpiufxkmv84p","playerOnName":"P. Rojas","playerOffId":"32f6rdu6sfpya3cly8u4yxtcl","playerOffName":"M. Sanhueza","subReason":"Tactical"},{"contestantId":"a6g25i52b5wrzwn7xb5g9u266","periodId":2,"timeMin":55,"lastUpdated":"2018-05-08T17:22:39Z","playerOnId":"40b61mee3nrxab9x2edq349n9","playerOnName":"R. Pereyra","playerOffId":"1g1jydib8m12mqnrm9ecqhlgp","playerOffName":"A. Vega","subReason":"Tactical"},{"contestantId":"26j8jh3je1ghdwsqxsbmre8d1","periodId":2,"timeMin":64,"lastUpdated":"2019-04-06T19:13:41Z","playerOnId":"9vo08gbunrfi15vqiir2m1s2y","playerOnName":"J. Ríos","playerOffId":"43krx180jhca256jl3lnzbcut","playerOffName":"F. Herrera","subReason":"Tactical"},{"contestantId":"a6g25i52b5wrzwn7xb5g9u266","periodId":2,"timeMin":69,"lastUpdated":"2019-10-12T23:22:07Z","playerOnId":"dhl46v91urj7l9k9c0lt3befp","playerOnName":"A. Rojas","playerOffId":"cvyktcienm8bc20etg6p0bxzp","playerOffName":"N. Rojas","subReason":"Tactical"},{"contestantId":"26j8jh3je1ghdwsqxsbmre8d1","periodId":2,"timeMin":72,"lastUpdated":"2018-05-08T17:23:32Z","playerOnId":"7s6gtijxr4vn9xhy6agwkcmsq","playerOnName":"J. Bordones","playerOffId":"bvz8cnkjrq65n9oku0zyqekfd","playerOffName":"C. Gutiérrez","subReason":"Tactical"},{"contestantId":"a6g25i52b5wrzwn7xb5g9u266","periodId":2,"timeMin":83,"lastUpdated":"2019-10-12T23:22:20Z","playerOnId":"agmniez6q8wmjd5ckny3tymsp","playerOnName":"N. Valenzuela","playerOffId":"7j5nyvpqq5fchjwx5pol3qevp","playerOffName":"C. Singer","subReason":"Tactical"}],"lineUp":[{"contestantId":"a6g25i52b5wrzwn7xb5g9u266","player":[{"playerId":"70lapiiy0a08fgyiymgrqxcr9","firstName":"Douglas Fabián","lastName":"Estay Hermosilla","matchName":"D. Estay","shirtNumber":2},{"playerId":"1k45t38sa2kl7d2f3zmjtih9l","firstName":"Alan Patricio","lastName":"Fernández Luna","matchName":"A. Fernández","shirtNumber":3},{"playerId":"16khuyqiy8jr8lhbf1fr2xxat","firstName":"Robert Matías","lastName":"González Núñez","matchName":"M. González","shirtNumber":5},{"playerId":"bf4buzfjh3y47jyu1x4u2b4d1","firstName":"Gustavo Andrés","lastName":"León Morales","matchName":"G. León","shirtNumber":15},{"playerId":"mb66a14gwr2xvom9pcmrjetx","firstName":"Juan","lastName":"López","matchName":"J. López","shirtNumber":17},{"playerId":"cvyktcienm8bc20etg6p0bxzp","firstName":"Nino Flavio","lastName":"Rojas Sagal","matchName":"N. Rojas","shirtNumber":9},{"playerId":"7j5nyvpqq5fchjwx5pol3qevp","firstName":"Christopher","lastName":"Singer Ossandón","matchName":"C. Singer","shirtNumber":23},{"playerId":"dx5urw0sc59agxirgzd77u4et","firstName":"Matias Alberto","lastName":"Sánchez Herrera","matchName":"M. Sánchez","shirtNumber":18},{"playerId":"c1ti50xzda1bjso28cmu5moyd","firstName":"Diego Andrés","lastName":"Tapia Rojas","matchName":"D. Tapia","shirtNumber":30},{"playerId":"1g1jydib8m12mqnrm9ecqhlgp","firstName":"Alexis","lastName":"Vega","matchName":"A. Vega","shirtNumber":11},{"playerId":"8q5tm1dmcoy18sm1pskh2eaga","firstName":"Carlos","lastName":"Villagrán","matchName":"C. Villagrán","shirtNumber":4},{"playerId":"ac6nd4x2d4yzwfpaqnv6wttxx","firstName":"José Francisco","lastName":"Durán Prieto","matchName":"J. Durán","shirtNumber":16,"position":"Substitute"},{"playerId":"arqv0aubc9t8g03h14c0xfjoq","firstName":"Bairon Gojan","lastName":"Monroy Arciego","matchName":"B. Monroy","shirtNumber":31,"position":"Substitute"},{"playerId":"40b61mee3nrxab9x2edq349n9","firstName":"José Ramiro","lastName":"Pereyra","matchName":"R. Pereyra","shirtNumber":10,"position":"Substitute"},{"playerId":"dhl46v91urj7l9k9c0lt3befp","firstName":"Alfredo Alejandro","lastName":"Rojas Acuña","matchName":"A. Rojas","shirtNumber":28,"position":"Substitute"},{"playerId":"4x430ve14ovbgxr3pieexn52i","firstName":"Benjamín","lastName":"Tapia Rojas","matchName":"B. Tapia","shirtNumber":40,"position":"Substitute"},{"playerId":"agmniez6q8wmjd5ckny3tymsp","firstName":"Nicolás","lastName":"Valenzuela","matchName":"N. Valenzuela","shirtNumber":29,"position":"Substitute"},{"playerId":"etw5r943qudni21l8iyval8lx","firstName":"Matías Silvio","lastName":"Ávila Sánchez","matchName":"M. Ávila","shirtNumber":20,"position":"Substitute"}],"teamOfficial":{"id":"4mpo2cpt7qwtw5dbw16h9ui8l","firstName":"Luis Eduardo","lastName":"Musrri Saravia","type":"manager"}},{"contestantId":"26j8jh3je1ghdwsqxsbmre8d1","player":[{"playerId":"6qer5dufqvyq4wwi9wxb4muol","firstName":"Diego Ignacio","lastName":"Cuéllar Vásquez","matchName":"D. Cuéllar","shirtNumber":9},{"playerId":"6ibka9a18wfm00fmhkzq7ymdx","firstName":"Matias","lastName":"Fabre","matchName":"M. Fabre","shirtNumber":8},{"playerId":"7l4dw99szy2c327ps9ej31y7e","firstName":"Francisco","lastName":"Godoy","matchName":"F. Godoy","shirtNumber":18},{"playerId":"bvz8cnkjrq65n9oku0zyqekfd","firstName":"Carlos Mauricio","lastName":"Gutiérrez Morales","matchName":"C. Gutiérrez","shirtNumber":5},{"playerId":"43krx180jhca256jl3lnzbcut","firstName":"Felipe Octavio","lastName":"Herrera Vasquez","matchName":"F. Herrera","shirtNumber":23},{"playerId":"26k7muwwn6yuiriv2kt9bhexh","firstName":"Carlos Andrés","lastName":"Julio Ramírez","matchName":"C. Julio","shirtNumber":1},{"playerId":"2s76t15xvjmcodt3tlkw9zg0l","firstName":"Jasson Lenin","lastName":"Lopez Contreras","matchName":"J. Lopez","shirtNumber":3},{"playerId":"3q7h5tiwrmnqriwi4cdxmbdud","firstName":"Giovanni Marcelo","lastName":"Narváez Narváez","matchName":"G. Narváez","shirtNumber":6},{"playerId":"a7qdf26f2pritmf7b7h87y1d6","firstName":"Manuel","lastName":"Paiva","matchName":"M. Paiva","shirtNumber":20},{"playerId":"vq3myz3qyz0s5eksi2f12uol","firstName":"Italo Eduardo","lastName":"Pizarro Dasso","matchName":"I. Pizarro","shirtNumber":4},{"playerId":"32f6rdu6sfpya3cly8u4yxtcl","firstName":"Matias Antonio","lastName":"Sanhueza Juica","matchName":"M. Sanhueza","shirtNumber":11},{"playerId":"3cubtd7tvzbdhqrlu36ryjc6i","firstName":"Felipe","lastName":"Araya","matchName":"F. Araya","shirtNumber":2,"position":"Substitute"},{"playerId":"2r3mr8ql57xj6c0vlqo01lfx1","firstName":"Jeff Alan","lastName":"Barria Huenchul","matchName":"J. Barria","shirtNumber":25,"position":"Substitute"},{"playerId":"7s6gtijxr4vn9xhy6agwkcmsq","firstName":"José","lastName":"Bordones","matchName":"J. Bordones","shirtNumber":14,"position":"Substitute"},{"playerId":"dyrbtgl17trirrpiufxkmv84p","firstName":"Pedro Antonio","lastName":"Rojas Corvalán","matchName":"P. Rojas","shirtNumber":7,"position":"Substitute"},{"playerId":"9vo08gbunrfi15vqiir2m1s2y","firstName":"Johao","lastName":"Ríos","matchName":"J. Ríos","shirtNumber":17,"position":"Substitute"}],"teamOfficial":{"id":"8cpvqbwpk2lst7putrwm89uxh","firstName":"Ramon","lastName":"Climent","type":"manager"}}],"matchDetailsExtra":{"matchOfficial":[{"id":"8wxmvv6ez4hs5aelkiw2ysnze","type":"Main","firstName":"Fabián","lastName":"Aedo"}]}}}