{
    "matchInfo": {
        "id": "cvdxv8c45192wumt7j1cxty0a",
        "coverageLevel": "13",
        "date": "2019-04-28Z",
        "time": "16:30:00Z",
        "week": "10",
        "lastUpdated": "2020-03-06T22:51:41Z",
        "description": "Unión La Calera vs O'Higgins",
        "sport": {
            "id": "289u5typ3vp4ifwh5thalohmq",
            "name": "Soccer"
        },
        "ruleset": {
            "id": "79plas4983031idr6vw83nuel",
            "name": "Men"
        },
        "competition": {
            "id": "2y8bntiif3a9y6gtmauv30gt",
            "name": "Primera División",
            "competitionCode": "PRD",
            "competitionFormat": "Domestic league",
            "country": {
                "id": "32tb8d7824xg4i0ybxzssczu0",
                "name": "Chile"
            }
        },
        "tournamentCalendar": {
            "id": "4q4irn3siv76err0gont5vhbe",
            "startDate": "2019-02-15Z",
            "endDate": "2019-12-22Z",
            "name": "2019"
        },
        "stage": {
            "id": "4qq0jqhksqr78lo9qa36ofdka",
            "formatId": "e2q01r9o9jwiq1fls93d1sslx",
            "startDate": "2019-02-15Z",
            "endDate": "2019-12-22Z",
            "name": "Regular Season"
        },
        "contestant": [
            {
                "id": "hfu6x1260h62zj7xl6cn95hx",
                "name": "Unión La Calera",
                "shortName": "U. La Calera",
                "officialName": "CD Unión La Calera",
                "code": "UCL",
                "position": "home",
                "country": {
                    "id": "32tb8d7824xg4i0ybxzssczu0",
                    "name": "Chile"
                }
            },
            {
                "id": "8rpjhpm2j1q7p40zfmlqpj8am",
                "name": "O'Higgins",
                "shortName": "O'Higgins",
                "officialName": "CD O'Higgins",
                "code": "OHI",
                "position": "away",
                "country": {
                    "id": "32tb8d7824xg4i0ybxzssczu0",
                    "name": "Chile"
                }
            }
        ],
        "venue": {
            "id": "1i2uslf0wsygp1h6uteshqcxj",
            "neutral": "no",
            "longName": "Estadio Municipal Nicolás Chahuán Nazar",
            "shortName": "Estadio Municipal Nicolás Chahuán Nazar"
        }
    },
    "liveData": {
        "matchDetails": {
            "periodId": 14,
            "matchStatus": "Played",
            "winner": "home",
            "matchLengthMin": 97,
            "matchLengthSec": 34,
            "period": [
                {
                    "id": 1,
                    "start": "2019-04-28T16:31:02Z",
                    "end": "2019-04-28T17:19:17Z",
                    "lengthMin": 48,
                    "lengthSec": 15
                },
                {
                    "id": 2,
                    "start": "2019-04-28T17:34:43Z",
                    "end": "2019-04-28T18:24:02Z",
                    "lengthMin": 49,
                    "lengthSec": 19
                }
            ],
            "scores": {
                "ht": {
                    "home": 0,
                    "away": 0
                },
                "ft": {
                    "home": 2,
                    "away": 0
                },
                "total": {
                    "home": 2,
                    "away": 0
                }
            }
        },
        "goal": [
            {
                "contestantId": "hfu6x1260h62zj7xl6cn95hx",
                "periodId": 2,
                "timeMin": 79,
                "timeMinSec": "78:35",
                "lastUpdated": "2019-09-16T13:40:08Z",
                "type": "G",
                "scorerId": "cb0h8bwynp5m7ijxiem6xtsyx",
                "scorerName": "T. Rodríguez",
                "assistPlayerId": "583d50xr2ktdxm8bnbmzsc9ud",
                "assistPlayerName": "M. Laba",
                "optaEventId": "1814410548",
                "homeScore": 1,
                "awayScore": 0
            },
            {
                "contestantId": "hfu6x1260h62zj7xl6cn95hx",
                "periodId": 2,
                "timeMin": 82,
                "timeMinSec": "81:23",
                "lastUpdated": "2019-09-16T13:39:52Z",
                "type": "G",
                "scorerId": "c8kksze0li7ndudwsxusykamt",
                "scorerName": "S. Zúñiga",
                "assistPlayerId": "da7i7u80skarx6vtsgajirs2d",
                "assistPlayerName": "W. Bou",
                "optaEventId": "2108796159",
                "homeScore": 2,
                "awayScore": 0
            }
        ],
        "card": [
            {
                "contestantId": "hfu6x1260h62zj7xl6cn95hx",
                "periodId": 2,
                "timeMin": 77,
                "timeMinSec": "76:45",
                "lastUpdated": "2019-09-16T13:39:52Z",
                "type": "YC",
                "playerId": "c8kksze0li7ndudwsxusykamt",
                "playerName": "S. Zúñiga",
                "optaEventId": "1751225878",
                "cardReason": "Foul"
            }
        ],
        "substitute": [
            {
                "contestantId": "hfu6x1260h62zj7xl6cn95hx",
                "periodId": 2,
                "timeMin": 63,
                "timeMinSec": "62:47",
                "lastUpdated": "2019-09-16T13:40:08Z",
                "playerOnId": "cb0h8bwynp5m7ijxiem6xtsyx",
                "playerOnName": "T. Rodríguez",
                "playerOffId": "4v5wc5fp4ow25o1cbhrr773l5",
                "playerOffName": "F. Lobos",
                "subReason": "Tactical"
            },
            {
                "contestantId": "8rpjhpm2j1q7p40zfmlqpj8am",
                "periodId": 2,
                "timeMin": 64,
                "timeMinSec": "63:12",
                "lastUpdated": "2019-09-16T13:38:37Z",
                "playerOnId": "9jhcjpr88roc0myzi39dkezth",
                "playerOnName": "F. Ramírez",
                "playerOffId": "6naix5aww70ttc0mx9j5jxuqx",
                "playerOffName": "A. Doffo",
                "subReason": "Tactical"
            },
            {
                "contestantId": "hfu6x1260h62zj7xl6cn95hx",
                "periodId": 2,
                "timeMin": 77,
                "timeMinSec": "76:06",
                "lastUpdated": "2019-09-16T13:39:52Z",
                "playerOnId": "c8kksze0li7ndudwsxusykamt",
                "playerOnName": "S. Zúñiga",
                "playerOffId": "82ffef6lzygelxn9swn5pqzca",
                "playerOffName": "J. Andía",
                "subReason": "Tactical"
            },
            {
                "contestantId": "8rpjhpm2j1q7p40zfmlqpj8am",
                "periodId": 2,
                "timeMin": 83,
                "timeMinSec": "82:10",
                "lastUpdated": "2019-09-16T13:38:32Z",
                "playerOnId": "tt0300qkkmgu52dbkxcaywut",
                "playerOnName": "R. López",
                "playerOffId": "1e994q9isbbc23tfb8riizm51",
                "playerOffName": "R. Osorio",
                "subReason": "Tactical"
            },
            {
                "contestantId": "hfu6x1260h62zj7xl6cn95hx",
                "periodId": 2,
                "timeMin": 83,
                "timeMinSec": "82:36",
                "lastUpdated": "2019-09-16T13:39:55Z",
                "playerOnId": "45oz154gekjf09w6oyv8glg45",
                "playerOnName": "C. Meneses",
                "playerOffId": "da7i7u80skarx6vtsgajirs2d",
                "playerOffName": "W. Bou",
                "subReason": "Tactical"
            },
            {
                "contestantId": "8rpjhpm2j1q7p40zfmlqpj8am",
                "periodId": 2,
                "timeMin": 86,
                "timeMinSec": "85:26",
                "lastUpdated": "2019-09-16T13:38:41Z",
                "playerOnId": "4rf8lr9ebnebwviw3spv6iyg9",
                "playerOnName": "M. Sepúlveda",
                "playerOffId": "2vl13a1bvpgufl0h2xmv3x1hx",
                "playerOffName": "A. Acevedo",
                "subReason": "Tactical"
            }
        ],
        "lineUp": [
            {
                "contestantId": "hfu6x1260h62zj7xl6cn95hx",
                "formationUsed": "4231",
                "player": [
                    {
                        "playerId": "9h6xf4ac4rpsjpummcdx26z9",
                        "firstName": "Augusto Martín",
                        "lastName": "Batalla Barga",
                        "matchName": "A. Batalla",
                        "shirtNumber": 22,
                        "position": "Goalkeeper",
                        "positionSide": "Centre",
                        "formationPlace": "1",
                        "stat": [
                            {
                                "type": "accuratePass",
                                "value": "21"
                            },
                            {
                                "type": "saves",
                                "value": "4"
                            },
                            {
                                "type": "goalKicks",
                                "value": "9"
                            },
                            {
                                "type": "totalPass",
                                "value": "25"
                            },
                            {
                                "type": "gameStarted",
                                "value": "1"
                            },
                            {
                                "type": "cleanSheet",
                                "value": "1"
                            },
                            {
                                "type": "minsPlayed",
                                "value": "90"
                            },
                            {
                                "type": "formationPlace",
                                "value": "1"
                            }
                        ]
                    },
                    {
                        "playerId": "156rs7mzlgizbt6swmpn9ybpx",
                        "firstName": "Érick",
                        "lastName": "Wiemberg Higuera",
                        "matchName": "É. Wiemberg",
                        "shirtNumber": 20,
                        "position": "Defender",
                        "positionSide": "Left",
                        "formationPlace": "3",
                        "stat": [
                            {
                                "type": "blockedScoringAtt",
                                "value": "1"
                            },
                            {
                                "type": "accuratePass",
                                "value": "36"
                            },
                            {
                                "type": "wonTackle",
                                "value": "5"
                            },
                            {
                                "type": "lostCorners",
                                "value": "1"
                            },
                            {
                                "type": "totalScoringAtt",
                                "value": "2"
                            },
                            {
                                "type": "totalThrows",
                                "value": "8"
                            },
                            {
                                "type": "totalPass",
                                "value": "43"
                            },
                            {
                                "type": "gameStarted",
                                "value": "1"
                            },
                            {
                                "type": "totalTackle",
                                "value": "7"
                            },
                            {
                                "type": "cleanSheet",
                                "value": "1"
                            },
                            {
                                "type": "shotOffTarget",
                                "value": "1"
                            },
                            {
                                "type": "minsPlayed",
                                "value": "90"
                            },
                            {
                                "type": "fouls",
                                "value": "1"
                            },
                            {
                                "type": "totalClearance",
                                "value": "4"
                            },
                            {
                                "type": "formationPlace",
                                "value": "3"
                            }
                        ]
                    },
                    {
                        "playerId": "dxwxm5jjbo5gnzx09oe63a8k5",
                        "firstName": "Pablo Andrés",
                        "lastName": "Alvarado",
                        "matchName": "P. Alvarado",
                        "shirtNumber": 2,
                        "position": "Defender",
                        "positionSide": "Left/Centre",
                        "formationPlace": "6",
                        "stat": [
                            {
                                "type": "accuratePass",
                                "value": "56"
                            },
                            {
                                "type": "wonTackle",
                                "value": "1"
                            },
                            {
                                "type": "wasFouled",
                                "value": "1"
                            },
                            {
                                "type": "totalPass",
                                "value": "66"
                            },
                            {
                                "type": "gameStarted",
                                "value": "1"
                            },
                            {
                                "type": "totalTackle",
                                "value": "4"
                            },
                            {
                                "type": "cleanSheet",
                                "value": "1"
                            },
                            {
                                "type": "minsPlayed",
                                "value": "90"
                            },
                            {
                                "type": "totalClearance",
                                "value": "2"
                            },
                            {
                                "type": "formationPlace",
                                "value": "6"
                            }
                        ]
                    },
                    {
                        "playerId": "d3s4hail4zq1sc81e0gjr6nrp",
                        "firstName": "Christian Alberto",
                        "lastName": "Vilches González",
                        "matchName": "C. Vilches",
                        "shirtNumber": 17,
                        "position": "Defender",
                        "positionSide": "Centre/Right",
                        "formationPlace": "5",
                        "stat": [
                            {
                                "type": "accuratePass",
                                "value": "42"
                            },
                            {
                                "type": "lostCorners",
                                "value": "1"
                            },
                            {
                                "type": "totalPass",
                                "value": "48"
                            },
                            {
                                "type": "gameStarted",
                                "value": "1"
                            },
                            {
                                "type": "totalTackle",
                                "value": "1"
                            },
                            {
                                "type": "cleanSheet",
                                "value": "1"
                            },
                            {
                                "type": "minsPlayed",
                                "value": "90"
                            },
                            {
                                "type": "totalClearance",
                                "value": "3"
                            },
                            {
                                "type": "formationPlace",
                                "value": "5"
                            }
                        ]
                    },
                    {
                        "playerId": "82ffef6lzygelxn9swn5pqzca",
                        "firstName": "Jonathan Wladimir",
                        "lastName": "Andía León",
                        "matchName": "J. Andía",
                        "shirtNumber": 6,
                        "position": "Defender",
                        "positionSide": "Right",
                        "formationPlace": "2",
                        "stat": [
                            {
                                "type": "accuratePass",
                                "value": "38"
                            },
                            {
                                "type": "wonTackle",
                                "value": "2"
                            },
                            {
                                "type": "totalScoringAtt",
                                "value": "2"
                            },
                            {
                                "type": "totalThrows",
                                "value": "4"
                            },
                            {
                                "type": "totalSubOff",
                                "value": "1"
                            },
                            {
                                "type": "totalPass",
                                "value": "42"
                            },
                            {
                                "type": "gameStarted",
                                "value": "1"
                            },
                            {
                                "type": "totalTackle",
                                "value": "3"
                            },
                            {
                                "type": "shotOffTarget",
                                "value": "2"
                            },
                            {
                                "type": "minsPlayed",
                                "value": "77"
                            },
                            {
                                "type": "totalClearance",
                                "value": "1"
                            },
                            {
                                "type": "formationPlace",
                                "value": "2"
                            }
                        ]
                    },
                    {
                        "playerId": "bn04vhl78qfknkl5fk84rkuz9",
                        "firstName": "Juan Andrés",
                        "lastName": "Leiva Mieres",
                        "matchName": "J. Leiva",
                        "shirtNumber": 11,
                        "position": "Defensive Midfielder",
                        "positionSide": "Left/Centre",
                        "formationPlace": "4",
                        "stat": [
                            {
                                "type": "accuratePass",
                                "value": "45"
                            },
                            {
                                "type": "wonTackle",
                                "value": "1"
                            },
                            {
                                "type": "wasFouled",
                                "value": "1"
                            },
                            {
                                "type": "totalScoringAtt",
                                "value": "3"
                            },
                            {
                                "type": "totalPass",
                                "value": "51"
                            },
                            {
                                "type": "gameStarted",
                                "value": "1"
                            },
                            {
                                "type": "totalTackle",
                                "value": "1"
                            },
                            {
                                "type": "cleanSheet",
                                "value": "1"
                            },
                            {
                                "type": "shotOffTarget",
                                "value": "3"
                            },
                            {
                                "type": "minsPlayed",
                                "value": "90"
                            },
                            {
                                "type": "fouls",
                                "value": "4"
                            },
                            {
                                "type": "formationPlace",
                                "value": "4"
                            }
                        ]
                    },
                    {
                        "playerId": "583d50xr2ktdxm8bnbmzsc9ud",
                        "firstName": "Matías Alejandro",
                        "lastName": "Laba",
                        "matchName": "M. Laba",
                        "shirtNumber": 5,
                        "position": "Defensive Midfielder",
                        "positionSide": "Centre/Right",
                        "formationPlace": "8",
                        "stat": [
                            {
                                "type": "accuratePass",
                                "value": "57"
                            },
                            {
                                "type": "wonTackle",
                                "value": "4"
                            },
                            {
                                "type": "wasFouled",
                                "value": "1"
                            },
                            {
                                "type": "lostCorners",
                                "value": "1"
                            },
                            {
                                "type": "goalAssist",
                                "value": "1"
                            },
                            {
                                "type": "totalPass",
                                "value": "60"
                            },
                            {
                                "type": "gameStarted",
                                "value": "1"
                            },
                            {
                                "type": "totalTackle",
                                "value": "7"
                            },
                            {
                                "type": "cleanSheet",
                                "value": "1"
                            },
                            {
                                "type": "minsPlayed",
                                "value": "90"
                            },
                            {
                                "type": "fouls",
                                "value": "4"
                            },
                            {
                                "type": "totalClearance",
                                "value": "2"
                            },
                            {
                                "type": "formationPlace",
                                "value": "8"
                            }
                        ]
                    },
                    {
                        "playerId": "4v5wc5fp4ow25o1cbhrr773l5",
                        "firstName": "César Franco",
                        "lastName": "Lobos Asman",
                        "matchName": "F. Lobos",
                        "shirtNumber": 18,
                        "position": "Attacking Midfielder",
                        "positionSide": "Left/Centre",
                        "stat": [
                            {
                                "type": "accuratePass",
                                "value": "13"
                            },
                            {
                                "type": "wonTackle",
                                "value": "2"
                            },
                            {
                                "type": "totalSubOff",
                                "value": "1"
                            },
                            {
                                "type": "totalPass",
                                "value": "18"
                            },
                            {
                                "type": "gameStarted",
                                "value": "1"
                            },
                            {
                                "type": "totalTackle",
                                "value": "2"
                            },
                            {
                                "type": "minsPlayed",
                                "value": "63"
                            },
                            {
                                "type": "totalClearance",
                                "value": "1"
                            },
                            {
                                "type": "formationPlace",
                                "value": "11"
                            }
                        ]
                    },
                    {
                        "playerId": "da7i7u80skarx6vtsgajirs2d",
                        "firstName": "Walter Ariel",
                        "lastName": "Bou",
                        "matchName": "W. Bou",
                        "shirtNumber": 29,
                        "position": "Attacking Midfielder",
                        "positionSide": "Centre",
                        "formationPlace": "10",
                        "stat": [
                            {
                                "type": "blockedScoringAtt",
                                "value": "1"
                            },
                            {
                                "type": "accuratePass",
                                "value": "23"
                            },
                            {
                                "type": "wasFouled",
                                "value": "1"
                            },
                            {
                                "type": "ontargetScoringAtt",
                                "value": "2"
                            },
                            {
                                "type": "totalScoringAtt",
                                "value": "4"
                            },
                            {
                                "type": "totalSubOff",
                                "value": "1"
                            },
                            {
                                "type": "goalAssist",
                                "value": "1"
                            },
                            {
                                "type": "totalPass",
                                "value": "28"
                            },
                            {
                                "type": "gameStarted",
                                "value": "1"
                            },
                            {
                                "type": "shotOffTarget",
                                "value": "1"
                            },
                            {
                                "type": "minsPlayed",
                                "value": "83"
                            },
                            {
                                "type": "fouls",
                                "value": "2"
                            },
                            {
                                "type": "formationPlace",
                                "value": "10"
                            }
                        ]
                    },
                    {
                        "playerId": "6rg499sllvyneyitrb66v7mj9",
                        "firstName": "Eugenio Horacio",
                        "lastName": "Isnaldo",
                        "matchName": "E. Isnaldo",
                        "shirtNumber": 19,
                        "position": "Attacking Midfielder",
                        "positionSide": "Centre/Right",
                        "stat": [
                            {
                                "type": "blockedScoringAtt",
                                "value": "2"
                            },
                            {
                                "type": "accuratePass",
                                "value": "40"
                            },
                            {
                                "type": "wonTackle",
                                "value": "3"
                            },
                            {
                                "type": "totalScoringAtt",
                                "value": "4"
                            },
                            {
                                "type": "totalPass",
                                "value": "45"
                            },
                            {
                                "type": "gameStarted",
                                "value": "1"
                            },
                            {
                                "type": "totalTackle",
                                "value": "4"
                            },
                            {
                                "type": "cleanSheet",
                                "value": "1"
                            },
                            {
                                "type": "shotOffTarget",
                                "value": "2"
                            },
                            {
                                "type": "wonCorners",
                                "value": "2"
                            },
                            {
                                "type": "minsPlayed",
                                "value": "90"
                            },
                            {
                                "type": "fouls",
                                "value": "1"
                            },
                            {
                                "type": "totalClearance",
                                "value": "2"
                            },
                            {
                                "type": "cornerTaken",
                                "value": "4"
                            },
                            {
                                "type": "formationPlace",
                                "value": "7"
                            }
                        ]
                    },
                    {
                        "playerId": "ehre8jxvvvlqbawddf8d8lgwl",
                        "firstName": "Marcelo Alejandro",
                        "lastName": "Larrondo Páez",
                        "matchName": "M. Larrondo",
                        "shirtNumber": 7,
                        "position": "Striker",
                        "positionSide": "Centre",
                        "formationPlace": "9",
                        "stat": [
                            {
                                "type": "blockedScoringAtt",
                                "value": "2"
                            },
                            {
                                "type": "accuratePass",
                                "value": "20"
                            },
                            {
                                "type": "wasFouled",
                                "value": "3"
                            },
                            {
                                "type": "ontargetScoringAtt",
                                "value": "1"
                            },
                            {
                                "type": "totalScoringAtt",
                                "value": "8"
                            },
                            {
                                "type": "totalPass",
                                "value": "23"
                            },
                            {
                                "type": "gameStarted",
                                "value": "1"
                            },
                            {
                                "type": "cleanSheet",
                                "value": "1"
                            },
                            {
                                "type": "shotOffTarget",
                                "value": "5"
                            },
                            {
                                "type": "wonCorners",
                                "value": "1"
                            },
                            {
                                "type": "minsPlayed",
                                "value": "90"
                            },
                            {
                                "type": "fouls",
                                "value": "2"
                            },
                            {
                                "type": "totalClearance",
                                "value": "2"
                            },
                            {
                                "type": "formationPlace",
                                "value": "9"
                            }
                        ]
                    },
                    {
                        "playerId": "awysskx5m1ww8dtzezu322xn9",
                        "firstName": "Erik",
                        "lastName": "Figueroa",
                        "matchName": "E. Figueroa",
                        "shirtNumber": 13,
                        "position": "Substitute",
                        "subPosition": "Defender",
                        "stat": [
                            {
                                "type": "formationPlace",
                                "value": "0"
                            }
                        ]
                    },
                    {
                        "playerId": "6ucunpb4yav9uibtb6ws2pk9h",
                        "firstName": "Lucas Raúl",
                        "lastName": "Giovini Schiapino",
                        "matchName": "L. Giovini",
                        "shirtNumber": 1,
                        "position": "Substitute",
                        "subPosition": "Goalkeeper",
                        "stat": [
                            {
                                "type": "formationPlace",
                                "value": "0"
                            }
                        ]
                    },
                    {
                        "playerId": "3xz9cyx54low8hq4xm2s04ogl",
                        "firstName": "Sebastián Ignacio",
                        "lastName": "Leyton Hevia",
                        "matchName": "S. Leyton",
                        "shirtNumber": 8,
                        "position": "Substitute",
                        "subPosition": "Midfielder",
                        "stat": [
                            {
                                "type": "formationPlace",
                                "value": "0"
                            }
                        ]
                    },
                    {
                        "playerId": "45oz154gekjf09w6oyv8glg45",
                        "firstName": "Claudio Andrés",
                        "lastName": "Meneses Cordero",
                        "matchName": "C. Meneses",
                        "shirtNumber": 4,
                        "position": "Substitute",
                        "subPosition": "Midfielder",
                        "stat": [
                            {
                                "type": "accuratePass",
                                "value": "2"
                            },
                            {
                                "type": "totalPass",
                                "value": "2"
                            },
                            {
                                "type": "totalSubOn",
                                "value": "1"
                            },
                            {
                                "type": "minsPlayed",
                                "value": "7"
                            },
                            {
                                "type": "totalClearance",
                                "value": "1"
                            },
                            {
                                "type": "formationPlace",
                                "value": "0"
                            }
                        ]
                    },
                    {
                        "playerId": "cb0h8bwynp5m7ijxiem6xtsyx",
                        "firstName": "Thomas",
                        "lastName": "Rodríguez Trogsar",
                        "matchName": "T. Rodríguez",
                        "shirtNumber": 21,
                        "position": "Substitute",
                        "subPosition": "Midfielder",
                        "stat": [
                            {
                                "type": "accuratePass",
                                "value": "10"
                            },
                            {
                                "type": "ontargetScoringAtt",
                                "value": "1"
                            },
                            {
                                "type": "totalScoringAtt",
                                "value": "1"
                            },
                            {
                                "type": "totalThrows",
                                "value": "2"
                            },
                            {
                                "type": "totalPass",
                                "value": "11"
                            },
                            {
                                "type": "goals",
                                "value": "1"
                            },
                            {
                                "type": "totalSubOn",
                                "value": "1"
                            },
                            {
                                "type": "wonCorners",
                                "value": "1"
                            },
                            {
                                "type": "minsPlayed",
                                "value": "27"
                            },
                            {
                                "type": "formationPlace",
                                "value": "0"
                            }
                        ]
                    },
                    {
                        "playerId": "ds2e8nkmztnxtfi9hnnefl1m2",
                        "firstName": "Esteban Cristóbal",
                        "lastName": "Valencia Reyes",
                        "matchName": "E. Valencia",
                        "shirtNumber": 27,
                        "position": "Substitute",
                        "subPosition": "Midfielder",
                        "stat": [
                            {
                                "type": "formationPlace",
                                "value": "0"
                            }
                        ]
                    },
                    {
                        "playerId": "c8kksze0li7ndudwsxusykamt",
                        "firstName": "Sebastián",
                        "lastName": "Zúñiga Fuenzalida",
                        "matchName": "S. Zúñiga",
                        "shirtNumber": 10,
                        "position": "Substitute",
                        "subPosition": "Midfielder",
                        "stat": [
                            {
                                "type": "accuratePass",
                                "value": "8"
                            },
                            {
                                "type": "yellowCard",
                                "value": "1"
                            },
                            {
                                "type": "ontargetScoringAtt",
                                "value": "1"
                            },
                            {
                                "type": "totalScoringAtt",
                                "value": "2"
                            },
                            {
                                "type": "totalPass",
                                "value": "8"
                            },
                            {
                                "type": "goals",
                                "value": "1"
                            },
                            {
                                "type": "totalSubOn",
                                "value": "1"
                            },
                            {
                                "type": "shotOffTarget",
                                "value": "1"
                            },
                            {
                                "type": "minsPlayed",
                                "value": "13"
                            },
                            {
                                "type": "fouls",
                                "value": "1"
                            },
                            {
                                "type": "formationPlace",
                                "value": "0"
                            }
                        ]
                    }
                ],
                "teamOfficial": {
                    "id": "6r1gg9m59i7oa1q47vydwh756",
                    "firstName": "Francisco",
                    "lastName": "Meneghini Correa",
                    "type": "manager"
                },
                "stat": [
                    {
                        "fh": "5",
                        "sh": "1",
                        "type": "blockedScoringAtt",
                        "value": "6"
                    },
                    {
                        "fh": "204",
                        "sh": "207",
                        "type": "accuratePass",
                        "value": "411"
                    },
                    {
                        "fh": "8",
                        "sh": "10",
                        "type": "wonTackle",
                        "value": "18"
                    },
                    {
                        "fh": "2",
                        "sh": "1",
                        "type": "lostCorners",
                        "value": "3"
                    },
                    {
                        "fh": "1",
                        "sh": "3",
                        "type": "saves",
                        "value": "4"
                    },
                    {
                        "fh": "2",
                        "sh": "3",
                        "type": "ontargetScoringAtt",
                        "value": "5"
                    },
                    {
                        "fh": "16",
                        "sh": "10",
                        "type": "totalScoringAtt",
                        "value": "26"
                    },
                    {
                        "fh": "0",
                        "sh": "3",
                        "type": "subsMade",
                        "value": "3"
                    },
                    {
                        "fh": "7",
                        "sh": "7",
                        "type": "totalThrows",
                        "value": "14"
                    },
                    {
                        "fh": "0",
                        "sh": "1",
                        "type": "totalYellowCard",
                        "value": "1"
                    },
                    {
                        "fh": "5",
                        "sh": "4",
                        "type": "goalKicks",
                        "value": "9"
                    },
                    {
                        "fh": "0",
                        "sh": "2",
                        "type": "goalAssist",
                        "value": "2"
                    },
                    {
                        "fh": "235",
                        "sh": "235",
                        "type": "totalPass",
                        "value": "470"
                    },
                    {
                        "fh": "0",
                        "sh": "2",
                        "type": "goals",
                        "value": "2"
                    },
                    {
                        "fh": "4",
                        "sh": "3",
                        "type": "fkFoulWon",
                        "value": "7"
                    },
                    {
                        "fh": "12",
                        "sh": "17",
                        "type": "totalTackle",
                        "value": "29"
                    },
                    {
                        "type": "cleanSheet",
                        "value": "1"
                    },
                    {
                        "fh": "9",
                        "sh": "6",
                        "type": "shotOffTarget",
                        "value": "15"
                    },
                    {
                        "fh": "7",
                        "sh": "8",
                        "type": "fkFoulLost",
                        "value": "15"
                    },
                    {
                        "fh": "0",
                        "sh": "4",
                        "type": "wonCorners",
                        "value": "4"
                    },
                    {
                        "fh": "56.9",
                        "sh": "53.9",
                        "type": "possessionPercentage",
                        "value": "55.3"
                    },
                    {
                        "fh": "9",
                        "sh": "9",
                        "type": "totalClearance",
                        "value": "18"
                    },
                    {
                        "fh": "0",
                        "sh": "4",
                        "type": "cornerTaken",
                        "value": "4"
                    },
                    {
                        "type": "formationUsed",
                        "value": "4231"
                    }
                ],
                "kit": {
                    "id": "1099",
                    "colour1": "#FF0000",
                    "type": "home"
                }
            },
            {
                "contestantId": "8rpjhpm2j1q7p40zfmlqpj8am",
                "formationUsed": "4141",
                "player": [
                    {
                        "playerId": "drz07oqwrot4amw308ykk3c9h",
                        "firstName": "Miguel Ángel",
                        "lastName": "Pinto Jérez",
                        "matchName": "M. Pinto",
                        "shirtNumber": 1,
                        "position": "Goalkeeper",
                        "positionSide": "Centre",
                        "formationPlace": "1",
                        "stat": [
                            {
                                "type": "accuratePass",
                                "value": "26"
                            },
                            {
                                "type": "goalsConceded",
                                "value": "2"
                            },
                            {
                                "type": "saves",
                                "value": "3"
                            },
                            {
                                "type": "goalKicks",
                                "value": "22"
                            },
                            {
                                "type": "totalPass",
                                "value": "34"
                            },
                            {
                                "type": "gameStarted",
                                "value": "1"
                            },
                            {
                                "type": "minsPlayed",
                                "value": "90"
                            },
                            {
                                "type": "totalClearance",
                                "value": "3"
                            },
                            {
                                "type": "formationPlace",
                                "value": "1"
                            }
                        ]
                    },
                    {
                        "playerId": "1e994q9isbbc23tfb8riizm51",
                        "firstName": "Raúl Andrés",
                        "lastName": "Osorio Medina",
                        "matchName": "R. Osorio",
                        "shirtNumber": 20,
                        "position": "Defender",
                        "positionSide": "Left",
                        "formationPlace": "3",
                        "stat": [
                            {
                                "type": "accuratePass",
                                "value": "18"
                            },
                            {
                                "type": "lostCorners",
                                "value": "1"
                            },
                            {
                                "type": "goalsConceded",
                                "value": "2"
                            },
                            {
                                "type": "totalThrows",
                                "value": "3"
                            },
                            {
                                "type": "totalSubOff",
                                "value": "1"
                            },
                            {
                                "type": "totalPass",
                                "value": "24"
                            },
                            {
                                "type": "gameStarted",
                                "value": "1"
                            },
                            {
                                "type": "totalTackle",
                                "value": "1"
                            },
                            {
                                "type": "minsPlayed",
                                "value": "83"
                            },
                            {
                                "type": "totalClearance",
                                "value": "4"
                            },
                            {
                                "type": "formationPlace",
                                "value": "3"
                            }
                        ]
                    },
                    {
                        "playerId": "9ng3r1au4q01ixq42sfn9x3h1",
                        "firstName": "Juan Eduardo",
                        "lastName": "Fuentes Jiménez",
                        "matchName": "J. Fuentes",
                        "shirtNumber": 6,
                        "position": "Defender",
                        "positionSide": "Left/Centre",
                        "formationPlace": "6",
                        "stat": [
                            {
                                "type": "accuratePass",
                                "value": "16"
                            },
                            {
                                "type": "wasFouled",
                                "value": "2"
                            },
                            {
                                "type": "lostCorners",
                                "value": "1"
                            },
                            {
                                "type": "goalsConceded",
                                "value": "2"
                            },
                            {
                                "type": "totalPass",
                                "value": "23"
                            },
                            {
                                "type": "gameStarted",
                                "value": "1"
                            },
                            {
                                "type": "minsPlayed",
                                "value": "90"
                            },
                            {
                                "type": "fouls",
                                "value": "1"
                            },
                            {
                                "type": "totalClearance",
                                "value": "6"
                            },
                            {
                                "type": "formationPlace",
                                "value": "6"
                            }
                        ]
                    },
                    {
                        "playerId": "2vl13a1bvpgufl0h2xmv3x1hx",
                        "firstName": "Albert Alejandro",
                        "lastName": "Acevedo Vergara",
                        "matchName": "A. Acevedo",
                        "shirtNumber": 3,
                        "position": "Defender",
                        "positionSide": "Centre/Right",
                        "formationPlace": "5",
                        "stat": [
                            {
                                "type": "accuratePass",
                                "value": "26"
                            },
                            {
                                "type": "wonTackle",
                                "value": "1"
                            },
                            {
                                "type": "goalsConceded",
                                "value": "2"
                            },
                            {
                                "type": "totalScoringAtt",
                                "value": "1"
                            },
                            {
                                "type": "totalSubOff",
                                "value": "1"
                            },
                            {
                                "type": "totalPass",
                                "value": "34"
                            },
                            {
                                "type": "gameStarted",
                                "value": "1"
                            },
                            {
                                "type": "totalTackle",
                                "value": "1"
                            },
                            {
                                "type": "shotOffTarget",
                                "value": "1"
                            },
                            {
                                "type": "minsPlayed",
                                "value": "86"
                            },
                            {
                                "type": "fouls",
                                "value": "1"
                            },
                            {
                                "type": "totalClearance",
                                "value": "3"
                            },
                            {
                                "type": "formationPlace",
                                "value": "5"
                            }
                        ]
                    },
                    {
                        "playerId": "7f1z0zw8ecsk04glhsdxl6ndh",
                        "firstName": "Paulo Cézar",
                        "lastName": "Magalhaes Lobos",
                        "matchName": "P. Magalhaes",
                        "shirtNumber": 8,
                        "position": "Defender",
                        "positionSide": "Right",
                        "formationPlace": "2",
                        "stat": [
                            {
                                "type": "blockedScoringAtt",
                                "value": "1"
                            },
                            {
                                "type": "accuratePass",
                                "value": "29"
                            },
                            {
                                "type": "wonTackle",
                                "value": "1"
                            },
                            {
                                "type": "goalsConceded",
                                "value": "2"
                            },
                            {
                                "type": "ontargetScoringAtt",
                                "value": "2"
                            },
                            {
                                "type": "totalScoringAtt",
                                "value": "3"
                            },
                            {
                                "type": "totalThrows",
                                "value": "13"
                            },
                            {
                                "type": "totalPass",
                                "value": "35"
                            },
                            {
                                "type": "gameStarted",
                                "value": "1"
                            },
                            {
                                "type": "totalTackle",
                                "value": "2"
                            },
                            {
                                "type": "minsPlayed",
                                "value": "90"
                            },
                            {
                                "type": "fouls",
                                "value": "1"
                            },
                            {
                                "type": "totalClearance",
                                "value": "1"
                            },
                            {
                                "type": "formationPlace",
                                "value": "2"
                            }
                        ]
                    },
                    {
                        "playerId": "b9b44wsl4d24yps6luijnhgix",
                        "firstName": "Tomás",
                        "lastName": "Alarcón Vergara",
                        "matchName": "T. Alarcón",
                        "shirtNumber": 2,
                        "position": "Defensive Midfielder",
                        "positionSide": "Centre",
                        "formationPlace": "4",
                        "stat": [
                            {
                                "type": "accuratePass",
                                "value": "40"
                            },
                            {
                                "type": "wonTackle",
                                "value": "3"
                            },
                            {
                                "type": "goalsConceded",
                                "value": "2"
                            },
                            {
                                "type": "totalPass",
                                "value": "47"
                            },
                            {
                                "type": "gameStarted",
                                "value": "1"
                            },
                            {
                                "type": "totalTackle",
                                "value": "4"
                            },
                            {
                                "type": "minsPlayed",
                                "value": "90"
                            },
                            {
                                "type": "totalClearance",
                                "value": "6"
                            },
                            {
                                "type": "formationPlace",
                                "value": "4"
                            }
                        ]
                    },
                    {
                        "playerId": "6naix5aww70ttc0mx9j5jxuqx",
                        "firstName": "Agustín",
                        "lastName": "Doffo",
                        "matchName": "A. Doffo",
                        "shirtNumber": 34,
                        "position": "Midfielder",
                        "positionSide": "Left",
                        "formationPlace": "11",
                        "stat": [
                            {
                                "type": "accuratePass",
                                "value": "20"
                            },
                            {
                                "type": "wasFouled",
                                "value": "3"
                            },
                            {
                                "type": "ontargetScoringAtt",
                                "value": "1"
                            },
                            {
                                "type": "totalScoringAtt",
                                "value": "1"
                            },
                            {
                                "type": "totalSubOff",
                                "value": "1"
                            },
                            {
                                "type": "totalPass",
                                "value": "29"
                            },
                            {
                                "type": "gameStarted",
                                "value": "1"
                            },
                            {
                                "type": "minsPlayed",
                                "value": "64"
                            },
                            {
                                "type": "fouls",
                                "value": "1"
                            },
                            {
                                "type": "cornerTaken",
                                "value": "1"
                            },
                            {
                                "type": "formationPlace",
                                "value": "11"
                            }
                        ]
                    },
                    {
                        "playerId": "27ng8lwfdgoymw9al0pdz70et",
                        "firstName": "Roberto Andrés",
                        "lastName": "Cereceda Guajardo",
                        "matchName": "R. Cereceda",
                        "shirtNumber": 17,
                        "position": "Midfielder",
                        "positionSide": "Left/Centre",
                        "formationPlace": "10",
                        "stat": [
                            {
                                "type": "accuratePass",
                                "value": "39"
                            },
                            {
                                "type": "wonTackle",
                                "value": "2"
                            },
                            {
                                "type": "wasFouled",
                                "value": "4"
                            },
                            {
                                "type": "lostCorners",
                                "value": "1"
                            },
                            {
                                "type": "goalsConceded",
                                "value": "2"
                            },
                            {
                                "type": "totalThrows",
                                "value": "4"
                            },
                            {
                                "type": "totalPass",
                                "value": "43"
                            },
                            {
                                "type": "gameStarted",
                                "value": "1"
                            },
                            {
                                "type": "totalTackle",
                                "value": "2"
                            },
                            {
                                "type": "wonCorners",
                                "value": "1"
                            },
                            {
                                "type": "minsPlayed",
                                "value": "90"
                            },
                            {
                                "type": "totalClearance",
                                "value": "1"
                            },
                            {
                                "type": "formationPlace",
                                "value": "10"
                            }
                        ]
                    },
                    {
                        "playerId": "4lavermlnoyl8wqjkwpx5uytx",
                        "firstName": "Ramón Ignacio",
                        "lastName": "Fernández",
                        "matchName": "R. Fernández",
                        "shirtNumber": 10,
                        "position": "Midfielder",
                        "positionSide": "Centre/Right",
                        "formationPlace": "8",
                        "stat": [
                            {
                                "type": "accuratePass",
                                "value": "50"
                            },
                            {
                                "type": "wonTackle",
                                "value": "3"
                            },
                            {
                                "type": "goalsConceded",
                                "value": "2"
                            },
                            {
                                "type": "totalScoringAtt",
                                "value": "1"
                            },
                            {
                                "type": "totalPass",
                                "value": "54"
                            },
                            {
                                "type": "gameStarted",
                                "value": "1"
                            },
                            {
                                "type": "totalTackle",
                                "value": "4"
                            },
                            {
                                "type": "shotOffTarget",
                                "value": "1"
                            },
                            {
                                "type": "minsPlayed",
                                "value": "90"
                            },
                            {
                                "type": "fouls",
                                "value": "1"
                            },
                            {
                                "type": "cornerTaken",
                                "value": "2"
                            },
                            {
                                "type": "formationPlace",
                                "value": "8"
                            }
                        ]
                    },
                    {
                        "playerId": "5i754yz270ysvlhywqor380r9",
                        "firstName": "José Luis",
                        "lastName": "Muñoz Muñoz",
                        "matchName": "J. Muñoz",
                        "shirtNumber": 7,
                        "position": "Midfielder",
                        "positionSide": "Right",
                        "formationPlace": "7",
                        "stat": [
                            {
                                "type": "blockedScoringAtt",
                                "value": "2"
                            },
                            {
                                "type": "accuratePass",
                                "value": "9"
                            },
                            {
                                "type": "goalsConceded",
                                "value": "2"
                            },
                            {
                                "type": "totalScoringAtt",
                                "value": "3"
                            },
                            {
                                "type": "totalPass",
                                "value": "11"
                            },
                            {
                                "type": "gameStarted",
                                "value": "1"
                            },
                            {
                                "type": "shotOffTarget",
                                "value": "1"
                            },
                            {
                                "type": "wonCorners",
                                "value": "1"
                            },
                            {
                                "type": "minsPlayed",
                                "value": "90"
                            },
                            {
                                "type": "fouls",
                                "value": "1"
                            },
                            {
                                "type": "formationPlace",
                                "value": "7"
                            }
                        ]
                    },
                    {
                        "playerId": "47ffwr98dn4yrrlh0y8q8cnah",
                        "firstName": "Maximiliano Nahuel",
                        "lastName": "Salas",
                        "matchName": "M. Salas",
                        "shirtNumber": 11,
                        "position": "Striker",
                        "positionSide": "Centre",
                        "formationPlace": "9",
                        "stat": [
                            {
                                "type": "blockedScoringAtt",
                                "value": "2"
                            },
                            {
                                "type": "accuratePass",
                                "value": "17"
                            },
                            {
                                "type": "wonTackle",
                                "value": "1"
                            },
                            {
                                "type": "wasFouled",
                                "value": "2"
                            },
                            {
                                "type": "lostCorners",
                                "value": "1"
                            },
                            {
                                "type": "goalsConceded",
                                "value": "2"
                            },
                            {
                                "type": "ontargetScoringAtt",
                                "value": "1"
                            },
                            {
                                "type": "totalScoringAtt",
                                "value": "4"
                            },
                            {
                                "type": "totalPass",
                                "value": "21"
                            },
                            {
                                "type": "gameStarted",
                                "value": "1"
                            },
                            {
                                "type": "totalTackle",
                                "value": "1"
                            },
                            {
                                "type": "totalOffside",
                                "value": "1"
                            },
                            {
                                "type": "shotOffTarget",
                                "value": "1"
                            },
                            {
                                "type": "wonCorners",
                                "value": "1"
                            },
                            {
                                "type": "minsPlayed",
                                "value": "90"
                            },
                            {
                                "type": "fouls",
                                "value": "2"
                            },
                            {
                                "type": "formationPlace",
                                "value": "9"
                            }
                        ]
                    },
                    {
                        "playerId": "be2kgk4nuajpwjrbvr2v0xhey",
                        "firstName": "Diego Humberto",
                        "lastName": "González Saavedra",
                        "matchName": "D. González",
                        "shirtNumber": 14,
                        "position": "Substitute",
                        "subPosition": "Midfielder",
                        "stat": [
                            {
                                "type": "formationPlace",
                                "value": "0"
                            }
                        ]
                    },
                    {
                        "playerId": "72u63348ho3blf54x6vh9vq0a",
                        "firstName": "Yerko",
                        "lastName": "González Santis",
                        "matchName": "Y. González",
                        "shirtNumber": 21,
                        "position": "Substitute",
                        "subPosition": "Midfielder",
                        "stat": [
                            {
                                "type": "formationPlace",
                                "value": "0"
                            }
                        ]
                    },
                    {
                        "playerId": "tt0300qkkmgu52dbkxcaywut",
                        "firstName": "Renzo",
                        "lastName": "López Patrón",
                        "matchName": "R. López",
                        "shirtNumber": 9,
                        "position": "Substitute",
                        "subPosition": "Attacker",
                        "stat": [
                            {
                                "type": "totalScoringAtt",
                                "value": "1"
                            },
                            {
                                "type": "totalPass",
                                "value": "1"
                            },
                            {
                                "type": "totalSubOn",
                                "value": "1"
                            },
                            {
                                "type": "shotOffTarget",
                                "value": "1"
                            },
                            {
                                "type": "minsPlayed",
                                "value": "7"
                            },
                            {
                                "type": "fouls",
                                "value": "1"
                            },
                            {
                                "type": "formationPlace",
                                "value": "0"
                            }
                        ]
                    },
                    {
                        "playerId": "9jhcjpr88roc0myzi39dkezth",
                        "firstName": "Fabrizio Antonio",
                        "lastName": "Ramírez Montero",
                        "matchName": "F. Ramírez",
                        "shirtNumber": 22,
                        "position": "Substitute",
                        "subPosition": "Midfielder",
                        "stat": [
                            {
                                "type": "accuratePass",
                                "value": "12"
                            },
                            {
                                "type": "wasFouled",
                                "value": "3"
                            },
                            {
                                "type": "goalsConceded",
                                "value": "2"
                            },
                            {
                                "type": "ontargetScoringAtt",
                                "value": "1"
                            },
                            {
                                "type": "totalScoringAtt",
                                "value": "2"
                            },
                            {
                                "type": "totalPass",
                                "value": "13"
                            },
                            {
                                "type": "totalSubOn",
                                "value": "1"
                            },
                            {
                                "type": "shotOffTarget",
                                "value": "1"
                            },
                            {
                                "type": "minsPlayed",
                                "value": "26"
                            },
                            {
                                "type": "totalClearance",
                                "value": "1"
                            },
                            {
                                "type": "formationPlace",
                                "value": "0"
                            }
                        ]
                    },
                    {
                        "playerId": "81744dro0kuegqxhut4p6hf55",
                        "firstName": "David Andrés",
                        "lastName": "Salazar Bustamante",
                        "matchName": "D. Salazar",
                        "shirtNumber": 25,
                        "position": "Substitute",
                        "subPosition": "Attacker",
                        "stat": [
                            {
                                "type": "formationPlace",
                                "value": "0"
                            }
                        ]
                    },
                    {
                        "playerId": "4rf8lr9ebnebwviw3spv6iyg9",
                        "firstName": "Matías Ignacio",
                        "lastName": "Sepúlveda Méndez",
                        "matchName": "M. Sepúlveda",
                        "shirtNumber": 26,
                        "position": "Substitute",
                        "subPosition": "Midfielder",
                        "stat": [
                            {
                                "type": "accuratePass",
                                "value": "3"
                            },
                            {
                                "type": "totalPass",
                                "value": "3"
                            },
                            {
                                "type": "totalSubOn",
                                "value": "1"
                            },
                            {
                                "type": "minsPlayed",
                                "value": "4"
                            },
                            {
                                "type": "formationPlace",
                                "value": "0"
                            }
                        ]
                    },
                    {
                        "playerId": "51xevz7yuqq9hdgl4ekrspbzd",
                        "firstName": "Luis Alfonso",
                        "lastName": "Ureta Medina",
                        "matchName": "L. Ureta",
                        "shirtNumber": 16,
                        "position": "Substitute",
                        "subPosition": "Goalkeeper",
                        "stat": [
                            {
                                "type": "formationPlace",
                                "value": "0"
                            }
                        ]
                    }
                ],
                "teamOfficial": {
                    "id": "a9121rv9p2ij5vjguhr2y37x1",
                    "firstName": "Marco Antonio",
                    "lastName": "Figueroa Montero",
                    "type": "manager"
                },
                "stat": [
                    {
                        "fh": "5",
                        "sh": "0",
                        "type": "blockedScoringAtt",
                        "value": "5"
                    },
                    {
                        "fh": "133",
                        "sh": "172",
                        "type": "accuratePass",
                        "value": "305"
                    },
                    {
                        "fh": "4",
                        "sh": "7",
                        "type": "wonTackle",
                        "value": "11"
                    },
                    {
                        "fh": "0",
                        "sh": "4",
                        "type": "lostCorners",
                        "value": "4"
                    },
                    {
                        "fh": "0",
                        "sh": "2",
                        "type": "goalsConceded",
                        "value": "2"
                    },
                    {
                        "fh": "2",
                        "sh": "1",
                        "type": "saves",
                        "value": "3"
                    },
                    {
                        "fh": "2",
                        "sh": "3",
                        "type": "ontargetScoringAtt",
                        "value": "5"
                    },
                    {
                        "fh": "9",
                        "sh": "7",
                        "type": "totalScoringAtt",
                        "value": "16"
                    },
                    {
                        "fh": "0",
                        "sh": "3",
                        "type": "subsMade",
                        "value": "3"
                    },
                    {
                        "fh": "13",
                        "sh": "7",
                        "type": "totalThrows",
                        "value": "20"
                    },
                    {
                        "fh": "13",
                        "sh": "9",
                        "type": "goalKicks",
                        "value": "22"
                    },
                    {
                        "fh": "173",
                        "sh": "199",
                        "type": "totalPass",
                        "value": "372"
                    },
                    {
                        "fh": "6",
                        "sh": "8",
                        "type": "fkFoulWon",
                        "value": "14"
                    },
                    {
                        "fh": "6",
                        "sh": "9",
                        "type": "totalTackle",
                        "value": "15"
                    },
                    {
                        "fh": "0",
                        "sh": "1",
                        "type": "totalOffside",
                        "value": "1"
                    },
                    {
                        "fh": "2",
                        "sh": "4",
                        "type": "shotOffTarget",
                        "value": "6"
                    },
                    {
                        "fh": "4",
                        "sh": "5",
                        "type": "fkFoulLost",
                        "value": "9"
                    },
                    {
                        "fh": "2",
                        "sh": "1",
                        "type": "wonCorners",
                        "value": "3"
                    },
                    {
                        "fh": "43.1",
                        "sh": "46.1",
                        "type": "possessionPercentage",
                        "value": "44.7"
                    },
                    {
                        "fh": "11",
                        "sh": "14",
                        "type": "totalClearance",
                        "value": "25"
                    },
                    {
                        "fh": "2",
                        "sh": "1",
                        "type": "cornerTaken",
                        "value": "3"
                    },
                    {
                        "type": "formationUsed",
                        "value": "4141"
                    }
                ],
                "kit": {
                    "id": "1089",
                    "colour1": "#00CCFF",
                    "colour2": "#FFFFFF",
                    "type": "home"
                }
            }
        ],
        "matchDetailsExtra": {
            "attendance": "4569",
            "matchOfficial": [
                {
                    "id": "anoszr3nonhgu2rok4ndw005x",
                    "type": "Main",
                    "firstName": "Piero",
                    "lastName": "Maza Gomez"
                }
            ]
        }
    }
}
