{"matchInfo":{"id":"7lh5tausij1w9zgj65blo8ju2","coverageLevel":"13","date":"2017-10-24Z","time":"22:15:00Z","lastUpdated":"2020-04-17T16:17:06Z","description":"River Plate vs Lanús","sport":{"id":"289u5typ3vp4ifwh5thalohmq","name":"Soccer"},"ruleset":{"id":"79plas4983031idr6vw83nuel","name":"Men"},"competition":{"id":"59tpnfrwnvhnhzmnvfyug68hj","name":"CONMEBOL Libertadores","competitionCode":"COL","competitionFormat":"International cup","country":{"id":"7ygvdgl31hirp07yeye1tvsut","name":"South America"}},"tournamentCalendar":{"id":"69niqv2h0l21uj1q1jowa7xt5","startDate":"2017-01-23Z","endDate":"2017-11-30Z","name":"2017"},"stage":{"id":"1x2flk9t89eh0hof4nu48ld5n","formatId":"2hrcobqge36fgp0q3wmc26f9x","startDate":"2017-10-25Z","endDate":"2017-11-02Z","name":"Semi-finals"},"contestant":[{"id":"115foion8jwrvp2e7xif675kx","name":"River Plate","shortName":"River Plate","officialName":"CA River Plate","code":"RIV","position":"home","country":{"id":"2vovxa97k7v7ofa85dah2xktb","name":"Argentina"}},{"id":"19ij50t7wklqr3w2bye5r7tp4","name":"Lanús","shortName":"Lanús","officialName":"CA Lanús","code":"LAN","position":"away","country":{"id":"2vovxa97k7v7ofa85dah2xktb","name":"Argentina"}}],"venue":{"id":"7xyfskcpghmryithcog91y6y3","neutral":"no","longName":"Estadio Monumental Antonio Vespucio Liberti","shortName":"Estadio Monumental Antonio Vespucio Liberti"}},"liveData":{"matchDetails":{"periodId":14,"matchStatus":"Played","winner":"home","relatedMatchId":"7lsf7zh9queqw5ewq4dw8r0bu","aggregateWinnerId":"19ij50t7wklqr3w2bye5r7tp4","matchLengthMin":95,"matchLengthSec":10,"period":[{"id":1,"start":"2017-10-24T22:16:19Z","end":"2017-10-24T23:02:24Z","lengthMin":46,"lengthSec":5},{"id":2,"start":"2017-10-24T23:19:44Z","end":"2017-10-25T00:08:49Z","lengthMin":49,"lengthSec":5}],"scores":{"ht":{"home":0,"away":0},"ft":{"home":1,"away":0},"total":{"home":1,"away":0},"aggregate":{"home":3,"away":4}}},"goal":[{"contestantId":"115foion8jwrvp2e7xif675kx","periodId":2,"timeMin":82,"lastUpdated":"2017-10-24T23:56:17Z","type":"G","scorerId":"78ksyb2h73ovpcqm9gsnghcd1","scorerName":"I. Scocco","optaEventId":"1166000214","homeScore":1,"awayScore":0}],"card":[{"contestantId":"19ij50t7wklqr3w2bye5r7tp4","periodId":2,"timeMin":73,"lastUpdated":"2017-10-24T23:48:12Z","type":"YC","playerId":"c1gaarepyyeofof5pda9ll4ut","playerName":"M. Velázquez","optaEventId":"1961115701","cardReason":"Foul"},{"contestantId":"115foion8jwrvp2e7xif675kx","periodId":2,"timeMin":77,"lastUpdated":"2017-10-24T23:52:22Z","type":"YC","playerId":"dhkccnrq8ipybi6qw789vwudx","playerName":"J. Pinola","optaEventId":"1714902395","cardReason":"Foul"}],"substitute":[{"contestantId":"115foion8jwrvp2e7xif675kx","periodId":2,"timeMin":65,"lastUpdated":"2018-05-30T20:59:47Z","playerOnId":"1caijgyxkokcvu2lnrh6x37c9","playerOnName":"N. De La Cruz","playerOffId":"5xg9armqib3ckx83uq5r9betx","playerOffName":"I. Fernández","subReason":"Tactical"},{"contestantId":"115foion8jwrvp2e7xif675kx","periodId":2,"timeMin":74,"lastUpdated":"2019-04-04T13:16:38Z","playerOnId":"e3jfzhvccluqns3fqzp7bmq51","playerOnName":"C. Auzqui","playerOffId":"8jf6iwkk15xlkmix318zn8set","playerOffName":"A. Rojas","subReason":"Tactical"},{"contestantId":"19ij50t7wklqr3w2bye5r7tp4","periodId":2,"timeMin":78,"lastUpdated":"2020-02-06T17:16:13Z","playerOnId":"aqce4nek34je3jttdgc9l31sl","playerOnName":"N. Aguirre","playerOffId":"c1gaarepyyeofof5pda9ll4ut","playerOffName":"M. Velázquez","subReason":"Tactical"},{"contestantId":"19ij50t7wklqr3w2bye5r7tp4","periodId":2,"timeMin":78,"lastUpdated":"2019-11-14T16:46:35Z","playerOnId":"7zxlvirhhicdubzsoftyvl591","playerOnName":"M. Rojas","playerOffId":"a0a6mrdprlut80ntwa33tl4ut","playerOffName":"A. Silva","subReason":"Tactical"},{"contestantId":"115foion8jwrvp2e7xif675kx","periodId":2,"timeMin":94,"lastUpdated":"2017-10-25T00:08:25Z","playerOnId":"6x4h2fbu0shpcvinoy7vqm47p","playerOnName":"M. Casco","playerOffId":"9qmyubxwvhhotzx7elbuzn7jd","playerOffName":"M. Saracchi","subReason":"Tactical"}],"lineUp":[{"contestantId":"115foion8jwrvp2e7xif675kx","player":[{"playerId":"9018q50kyhc7muchd8gls6sb9","firstName":"Germán Darío","lastName":"Lux","matchName":"G. Lux","shirtNumber":12,"position":"Goalkeeper","positionSide":"Centre","stat":[{"type":"accuratePass","value":"8"},{"type":"goalKicks","value":"3"},{"type":"totalPass","value":"14"},{"type":"gameStarted","value":"1"},{"type":"cleanSheet","value":"1"},{"type":"minsPlayed","value":"90"},{"type":"formationPlace","value":"1"}]},{"playerId":"9qmyubxwvhhotzx7elbuzn7jd","firstName":"Marcelo Josemir","lastName":"Saracchi Pintos","matchName":"M. Saracchi","shirtNumber":3,"position":"Defender","positionSide":"Left","stat":[{"type":"accuratePass","value":"37"},{"type":"wonTackle","value":"5"},{"type":"totalThrows","value":"5"},{"type":"totalSubOff","value":"1"},{"type":"totalPass","value":"44"},{"type":"gameStarted","value":"1"},{"type":"totalTackle","value":"5"},{"type":"wonCorners","value":"1"},{"type":"minsPlayed","value":"89"},{"type":"fouls","value":"2"},{"type":"totalClearance","value":"2"},{"type":"formationPlace","value":"3"}]},{"playerId":"dhkccnrq8ipybi6qw789vwudx","firstName":"Javier Horacio","lastName":"Pinola","matchName":"J. Pinola","shirtNumber":22,"position":"Defender","positionSide":"Left/Centre","stat":[{"type":"accuratePass","value":"76"},{"type":"wonTackle","value":"4"},{"type":"wasFouled","value":"1"},{"type":"yellowCard","value":"1"},{"type":"totalScoringAtt","value":"1"},{"type":"totalPass","value":"85"},{"type":"gameStarted","value":"1"},{"type":"totalTackle","value":"5"},{"type":"cleanSheet","value":"1"},{"type":"shotOffTarget","value":"1"},{"type":"minsPlayed","value":"90"},{"type":"fouls","value":"2"},{"type":"totalClearance","value":"2"},{"type":"formationPlace","value":"6"}]},{"playerId":"c98gkh46mjpyhbsdedf9uc5","firstName":"Jonathan Ramón","lastName":"Maidana","matchName":"J. Maidana","shirtNumber":2,"position":"Defender","positionSide":"Centre/Right","stat":[{"type":"accuratePass","value":"48"},{"type":"wasFouled","value":"1"},{"type":"lostCorners","value":"2"},{"type":"ontargetScoringAtt","value":"1"},{"type":"totalScoringAtt","value":"1"},{"type":"totalPass","value":"51"},{"type":"gameStarted","value":"1"},{"type":"totalTackle","value":"1"},{"type":"cleanSheet","value":"1"},{"type":"minsPlayed","value":"90"},{"type":"fouls","value":"1"},{"type":"totalClearance","value":"5"},{"type":"formationPlace","value":"5"}]},{"playerId":"1y74tse0vpdxanxf152cc8jjd","firstName":"Gonzalo Ariel","lastName":"Montiel","matchName":"G. Montiel","shirtNumber":29,"position":"Defender","positionSide":"Right","stat":[{"type":"accuratePass","value":"41"},{"type":"totalThrows","value":"15"},{"type":"totalPass","value":"53"},{"type":"gameStarted","value":"1"},{"type":"totalTackle","value":"1"},{"type":"cleanSheet","value":"1"},{"type":"minsPlayed","value":"90"},{"type":"fouls","value":"1"},{"type":"totalClearance","value":"1"},{"type":"formationPlace","value":"2"}]},{"playerId":"8jf6iwkk15xlkmix318zn8set","firstName":"Ariel Mauricio","lastName":"Rojas","matchName":"A. Rojas","shirtNumber":16,"position":"Defensive Midfielder","positionSide":"Left","stat":[{"type":"accuratePass","value":"20"},{"type":"wonTackle","value":"2"},{"type":"wasFouled","value":"1"},{"type":"totalThrows","value":"2"},{"type":"totalSubOff","value":"1"},{"type":"totalPass","value":"29"},{"type":"gameStarted","value":"1"},{"type":"totalTackle","value":"5"},{"type":"wonCorners","value":"2"},{"type":"minsPlayed","value":"74"},{"type":"cornerTaken","value":"2"},{"type":"formationPlace","value":"11"}]},{"playerId":"b0f2mh60px8penl9m7d5q6pjp","firstName":"Leonardo Daniel","lastName":"Ponzio","matchName":"L. Ponzio","shirtNumber":23,"position":"Defensive Midfielder","positionSide":"Centre","stat":[{"type":"accuratePass","value":"68"},{"type":"wasFouled","value":"1"},{"type":"totalPass","value":"72"},{"type":"gameStarted","value":"1"},{"type":"cleanSheet","value":"1"},{"type":"minsPlayed","value":"90"},{"type":"fouls","value":"3"},{"type":"formationPlace","value":"4"}]},{"playerId":"cpvhvr7q1z8ogtgloq9qafahh","firstName":"Enzo Nicolás","lastName":"Pérez","matchName":"E. Pérez","shirtNumber":24,"position":"Defensive Midfielder","positionSide":"Right","stat":[{"type":"accuratePass","value":"82"},{"type":"wasFouled","value":"2"},{"type":"lostCorners","value":"1"},{"type":"totalScoringAtt","value":"1"},{"type":"totalThrows","value":"2"},{"type":"totalPass","value":"90"},{"type":"gameStarted","value":"1"},{"type":"totalTackle","value":"2"},{"type":"cleanSheet","value":"1"},{"type":"shotOffTarget","value":"1"},{"type":"wonCorners","value":"1"},{"type":"minsPlayed","value":"90"},{"type":"fouls","value":"1"},{"type":"totalClearance","value":"3"},{"type":"formationPlace","value":"7"}]},{"playerId":"5xg9armqib3ckx83uq5r9betx","firstName":"Ignacio Martín","lastName":"Fernández","matchName":"I. Fernández","shirtNumber":26,"position":"Attacking Midfielder","positionSide":"Centre","stat":[{"type":"accuratePass","value":"26"},{"type":"wasFouled","value":"1"},{"type":"lostCorners","value":"1"},{"type":"totalSubOff","value":"1"},{"type":"totalPass","value":"32"},{"type":"gameStarted","value":"1"},{"type":"minsPlayed","value":"65"},{"type":"totalClearance","value":"2"},{"type":"formationPlace","value":"8"}]},{"playerId":"78ksyb2h73ovpcqm9gsnghcd1","firstName":"Ignacio Martín","lastName":"Scocco","matchName":"I. Scocco","shirtNumber":11,"position":"Striker","positionSide":"Left/Centre","stat":[{"type":"blockedScoringAtt","value":"1"},{"type":"accuratePass","value":"14"},{"type":"wonTackle","value":"2"},{"type":"wasFouled","value":"1"},{"type":"ontargetScoringAtt","value":"3"},{"type":"totalScoringAtt","value":"5"},{"type":"totalPass","value":"17"},{"type":"goals","value":"1"},{"type":"gameStarted","value":"1"},{"type":"totalTackle","value":"2"},{"type":"cleanSheet","value":"1"},{"type":"shotOffTarget","value":"1"},{"type":"wonCorners","value":"1"},{"type":"minsPlayed","value":"90"},{"type":"fouls","value":"1"},{"type":"totalClearance","value":"1"},{"type":"formationPlace","value":"10"}]},{"playerId":"ddb6de7pli57w8z163ztwczx1","firstName":"Gonzalo Nicolás","lastName":"Martínez","matchName":"G. Martínez","shirtNumber":10,"position":"Striker","positionSide":"Centre/Right","stat":[{"type":"blockedScoringAtt","value":"1"},{"type":"accuratePass","value":"35"},{"type":"wonTackle","value":"2"},{"type":"wasFouled","value":"4"},{"type":"ontargetScoringAtt","value":"1"},{"type":"totalScoringAtt","value":"4"},{"type":"totalThrows","value":"2"},{"type":"totalPass","value":"43"},{"type":"gameStarted","value":"1"},{"type":"totalTackle","value":"3"},{"type":"cleanSheet","value":"1"},{"type":"shotOffTarget","value":"2"},{"type":"wonCorners","value":"3"},{"type":"minsPlayed","value":"90"},{"type":"fouls","value":"3"},{"type":"cornerTaken","value":"6"},{"type":"formationPlace","value":"9"}]},{"playerId":"e3jfzhvccluqns3fqzp7bmq51","firstName":"Carlos Daniel","lastName":"Auzqui","matchName":"C. Auzqui","shirtNumber":17,"position":"Substitute","subPosition":"Attacker","stat":[{"type":"accuratePass","value":"4"},{"type":"wonTackle","value":"2"},{"type":"totalThrows","value":"1"},{"type":"totalPass","value":"4"},{"type":"totalTackle","value":"2"},{"type":"totalSubOn","value":"1"},{"type":"minsPlayed","value":"16"},{"type":"formationPlace","value":"0"}]},{"playerId":"8azbst6ntfo311m8bvyyb4dm1","firstName":"Alexander Nahuel","lastName":"Barboza Ullúa","matchName":"A. Barboza","shirtNumber":5,"position":"Substitute","subPosition":"Defender","stat":[{"type":"formationPlace","value":"0"}]},{"playerId":"9h6xf4ac4rpsjpummcdx26z9","firstName":"Augusto Martín","lastName":"Batalla Barga","matchName":"A. Batalla","shirtNumber":1,"position":"Substitute","subPosition":"Goalkeeper","stat":[{"type":"formationPlace","value":"0"}]},{"playerId":"2x5f35hk2urqlgoito1vgb3yt","firstName":"Rafael Santos","lastName":"Borré Maury","matchName":"R. Borré","shirtNumber":19,"position":"Substitute","subPosition":"Attacker","stat":[{"type":"formationPlace","value":"0"}]},{"playerId":"6x4h2fbu0shpcvinoy7vqm47p","firstName":"Milton","lastName":"Casco","matchName":"M. Casco","shirtNumber":20,"position":"Substitute","subPosition":"Defender","stat":[{"type":"totalSubOn","value":"1"},{"type":"minsPlayed","value":"1"},{"type":"formationPlace","value":"0"}]},{"playerId":"1caijgyxkokcvu2lnrh6x37c9","firstName":"Diego Nicolás","lastName":"De La Cruz Arcosa","matchName":"N. De La Cruz","shirtNumber":14,"position":"Substitute","subPosition":"Midfielder","stat":[{"type":"accuratePass","value":"9"},{"type":"wonTackle","value":"1"},{"type":"totalPass","value":"11"},{"type":"totalTackle","value":"1"},{"type":"totalSubOn","value":"1"},{"type":"minsPlayed","value":"25"},{"type":"fouls","value":"2"},{"type":"formationPlace","value":"0"}]},{"playerId":"d4oe6in70cylxxxqwp1m50hcl","firstName":"Iván","lastName":"Rossi","matchName":"I. Rossi","shirtNumber":21,"position":"Substitute","subPosition":"Midfielder","stat":[{"type":"formationPlace","value":"0"}]}],"teamOfficial":{"id":"e3jm0i6dnbmddcq4nl15n2or9","firstName":"Marcelo Daniel","lastName":"Gallardo","type":"manager"},"stat":[{"fh":"0","sh":"2","type":"blockedScoringAtt","value":"2"},{"fh":"226","sh":"242","type":"accuratePass","value":"468"},{"fh":"10","sh":"8","type":"wonTackle","value":"18"},{"fh":"4","sh":"0","type":"lostCorners","value":"4"},{"fh":"3","sh":"2","type":"ontargetScoringAtt","value":"5"},{"fh":"7","sh":"5","type":"totalScoringAtt","value":"12"},{"fh":"0","sh":"3","type":"subsMade","value":"3"},{"fh":"16","sh":"11","type":"totalThrows","value":"27"},{"fh":"0","sh":"1","type":"totalYellowCard","value":"1"},{"fh":"2","sh":"1","type":"goalKicks","value":"3"},{"fh":"267","sh":"278","type":"totalPass","value":"545"},{"fh":"0","sh":"1","type":"goals","value":"1"},{"fh":"4","sh":"8","type":"fkFoulWon","value":"12"},{"fh":"15","sh":"12","type":"totalTackle","value":"27"},{"type":"cleanSheet","value":"1"},{"fh":"4","sh":"1","type":"shotOffTarget","value":"5"},{"fh":"7","sh":"9","type":"fkFoulLost","value":"16"},{"fh":"4","sh":"4","type":"wonCorners","value":"8"},{"fh":"55.3","sh":"66.1","type":"possessionPercentage","value":"60.3"},{"fh":"10","sh":"6","type":"totalClearance","value":"16"},{"fh":"4","sh":"4","type":"cornerTaken","value":"8"},{"type":"formationUsed","value":"4312"}]},{"contestantId":"19ij50t7wklqr3w2bye5r7tp4","player":[{"playerId":"5e1an2e7bnk0269e1tvislv4l","firstName":"Esteban Maximiliano","lastName":"Andrada","matchName":"E. Andrada","shirtNumber":28,"position":"Goalkeeper","positionSide":"Centre","stat":[{"type":"accuratePass","value":"25"},{"type":"wasFouled","value":"1"},{"type":"goalsConceded","value":"1"},{"type":"saves","value":"4"},{"type":"goalKicks","value":"9"},{"type":"totalPass","value":"43"},{"type":"gameStarted","value":"1"},{"type":"minsPlayed","value":"90"},{"type":"formationPlace","value":"1"}]},{"playerId":"c1gaarepyyeofof5pda9ll4ut","firstName":"Maximiliano Nicolás","lastName":"Velázquez","matchName":"M. Velázquez","shirtNumber":3,"position":"Defender","positionSide":"Left","stat":[{"type":"blockedScoringAtt","value":"2"},{"type":"accuratePass","value":"27"},{"type":"wonTackle","value":"4"},{"type":"yellowCard","value":"1"},{"type":"totalScoringAtt","value":"2"},{"type":"totalThrows","value":"6"},{"type":"totalSubOff","value":"1"},{"type":"totalPass","value":"36"},{"type":"gameStarted","value":"1"},{"type":"totalTackle","value":"4"},{"type":"wonCorners","value":"1"},{"type":"minsPlayed","value":"78"},{"type":"fouls","value":"4"},{"type":"formationPlace","value":"3"}]},{"playerId":"9cpcsx3gif1oioywg4tcwsgyd","firstName":"Diego Luis","lastName":"Braghieri","matchName":"D. Braghieri","shirtNumber":6,"position":"Defender","positionSide":"Left/Centre","stat":[{"type":"accuratePass","value":"25"},{"type":"wonTackle","value":"3"},{"type":"lostCorners","value":"4"},{"type":"goalsConceded","value":"1"},{"type":"totalPass","value":"29"},{"type":"gameStarted","value":"1"},{"type":"totalTackle","value":"3"},{"type":"wonCorners","value":"1"},{"type":"minsPlayed","value":"90"},{"type":"totalClearance","value":"6"},{"type":"formationPlace","value":"6"}]},{"playerId":"7ibefflfdnau78xxjjr6pchjp","firstName":"Rolando","lastName":"García Guerreño","matchName":"R. García","shirtNumber":23,"position":"Defender","positionSide":"Centre/Right","stat":[{"type":"accuratePass","value":"36"},{"type":"wasFouled","value":"1"},{"type":"goalsConceded","value":"1"},{"type":"totalPass","value":"42"},{"type":"gameStarted","value":"1"},{"type":"minsPlayed","value":"90"},{"type":"fouls","value":"1"},{"type":"totalClearance","value":"6"},{"type":"formationPlace","value":"5"}]},{"playerId":"1k5v5kh5z0mh8386t9bda0h5h","firstName":"José Luis","lastName":"Gómez","matchName":"J. Gómez","shirtNumber":4,"position":"Defender","positionSide":"Right","stat":[{"type":"accuratePass","value":"32"},{"type":"wonTackle","value":"1"},{"type":"lostCorners","value":"3"},{"type":"goalsConceded","value":"1"},{"type":"totalThrows","value":"15"},{"type":"totalPass","value":"42"},{"type":"gameStarted","value":"1"},{"type":"totalTackle","value":"2"},{"type":"minsPlayed","value":"90"},{"type":"totalClearance","value":"2"},{"type":"formationPlace","value":"2"}]},{"playerId":"anfnhwj59gz4b6xkwv7h4a95h","firstName":"Nicolás","lastName":"Pasquini","matchName":"N. Pasquini","shirtNumber":21,"position":"Midfielder","positionSide":"Left/Centre","stat":[{"type":"accuratePass","value":"17"},{"type":"wonTackle","value":"2"},{"type":"wasFouled","value":"1"},{"type":"goalsConceded","value":"1"},{"type":"totalThrows","value":"1"},{"type":"totalPass","value":"24"},{"type":"gameStarted","value":"1"},{"type":"totalTackle","value":"2"},{"type":"minsPlayed","value":"90"},{"type":"cornerTaken","value":"2"},{"type":"formationPlace","value":"8"}]},{"playerId":"xc9s0mer4os7nzzcxlrhy6z9","firstName":"Iván José","lastName":"Marcone","matchName":"I. Marcone","shirtNumber":30,"position":"Midfielder","positionSide":"Centre","stat":[{"type":"accuratePass","value":"33"},{"type":"wonTackle","value":"3"},{"type":"wasFouled","value":"1"},{"type":"goalsConceded","value":"1"},{"type":"totalPass","value":"38"},{"type":"gameStarted","value":"1"},{"type":"totalTackle","value":"5"},{"type":"minsPlayed","value":"90"},{"type":"formationPlace","value":"4"}]},{"playerId":"2lt1nv41y8cq3o3pjik3eems5","firstName":"Román Fernando","lastName":"Martínez","matchName":"R. Martínez","shirtNumber":10,"position":"Midfielder","positionSide":"Centre/Right","stat":[{"type":"accuratePass","value":"35"},{"type":"wonTackle","value":"1"},{"type":"wasFouled","value":"2"},{"type":"goalsConceded","value":"1"},{"type":"totalPass","value":"43"},{"type":"gameStarted","value":"1"},{"type":"totalTackle","value":"2"},{"type":"minsPlayed","value":"90"},{"type":"fouls","value":"2"},{"type":"totalClearance","value":"2"},{"type":"formationPlace","value":"7"}]},{"playerId":"e5s9etyhxetj9tgzom2t9l42d","firstName":"Lautaro Germán","lastName":"Acosta","matchName":"L. Acosta","shirtNumber":7,"position":"Striker","positionSide":"Left/Centre","stat":[{"type":"accuratePass","value":"12"},{"type":"wonTackle","value":"1"},{"type":"wasFouled","value":"3"},{"type":"lostCorners","value":"1"},{"type":"goalsConceded","value":"1"},{"type":"totalPass","value":"20"},{"type":"gameStarted","value":"1"},{"type":"totalTackle","value":"1"},{"type":"totalOffside","value":"1"},{"type":"wonCorners","value":"1"},{"type":"minsPlayed","value":"90"},{"type":"fouls","value":"3"},{"type":"formationPlace","value":"11"}]},{"playerId":"e5y8zv46n6oczxit9u82xp32t","firstName":"José Gustavo","lastName":"Sand","matchName":"J. Sand","shirtNumber":9,"position":"Striker","positionSide":"Centre","stat":[{"type":"accuratePass","value":"18"},{"type":"wasFouled","value":"5"},{"type":"goalsConceded","value":"1"},{"type":"totalPass","value":"25"},{"type":"gameStarted","value":"1"},{"type":"minsPlayed","value":"90"},{"type":"fouls","value":"2"},{"type":"formationPlace","value":"9"}]},{"playerId":"a0a6mrdprlut80ntwa33tl4ut","firstName":"Alejandro Daniel","lastName":"Silva González","matchName":"A. Silva","shirtNumber":16,"position":"Striker","positionSide":"Centre/Right","stat":[{"type":"accuratePass","value":"14"},{"type":"wonTackle","value":"1"},{"type":"wasFouled","value":"1"},{"type":"totalSubOff","value":"1"},{"type":"totalPass","value":"19"},{"type":"gameStarted","value":"1"},{"type":"totalTackle","value":"2"},{"type":"wonCorners","value":"1"},{"type":"minsPlayed","value":"78"},{"type":"cornerTaken","value":"2"},{"type":"formationPlace","value":"10"}]},{"playerId":"aqce4nek34je3jttdgc9l31sl","firstName":"Nicolás Diego","lastName":"Aguirre","matchName":"N. Aguirre","shirtNumber":19,"position":"Substitute","subPosition":"Midfielder","stat":[{"type":"accuratePass","value":"3"},{"type":"goalsConceded","value":"1"},{"type":"totalPass","value":"5"},{"type":"totalSubOn","value":"1"},{"type":"minsPlayed","value":"12"},{"type":"fouls","value":"1"},{"type":"formationPlace","value":"0"}]},{"playerId":"bx2xiq6j7y053xs7a4cr0qh1x","firstName":"Luis Marcelo","lastName":"Herrera","matchName":"M. Herrera","shirtNumber":2,"position":"Substitute","subPosition":"Defender","stat":[{"type":"formationPlace","value":"0"}]},{"playerId":"1o8ut64m3rjez52erwtvbbdnt","firstName":"Leandro Isaac","lastName":"Maciel","matchName":"L. Maciel","shirtNumber":24,"position":"Substitute","subPosition":"Midfielder","stat":[{"type":"formationPlace","value":"0"}]},{"playerId":"cyfn1255tmqkoh4ra3qcme1g5","firstName":"Fernando","lastName":"Monetti","matchName":"F. Monetti","shirtNumber":1,"position":"Substitute","subPosition":"Goalkeeper","stat":[{"type":"formationPlace","value":"0"}]},{"playerId":"d42nqefiqme45lyi9mtclhtjp","firstName":"Damián Marcelino","lastName":"Moreno","matchName":"D. Moreno","shirtNumber":25,"position":"Substitute","subPosition":"Attacker","stat":[{"type":"formationPlace","value":"0"}]},{"playerId":"7zxlvirhhicdubzsoftyvl591","firstName":"Matías Nicolás","lastName":"Rojas Romero","matchName":"M. Rojas","shirtNumber":14,"position":"Substitute","subPosition":"Midfielder","stat":[{"type":"accuratePass","value":"1"},{"type":"wonTackle","value":"1"},{"type":"goalsConceded","value":"1"},{"type":"totalPass","value":"2"},{"type":"totalTackle","value":"1"},{"type":"totalSubOn","value":"1"},{"type":"minsPlayed","value":"12"},{"type":"fouls","value":"1"},{"type":"formationPlace","value":"0"}]},{"playerId":"3cyelie3ncvbo2j5n874p5uxh","firstName":"Santiago","lastName":"Zurbriggen","matchName":"S. Zurbriggen","shirtNumber":22,"position":"Substitute","subPosition":"Defender","stat":[{"type":"formationPlace","value":"0"}]}],"teamOfficial":{"id":"9rem4vr604rzys1emihtiu3th","firstName":"Jorge Francisco","lastName":"Almirón Quintana","type":"manager"},"stat":[{"fh":"0","sh":"2","type":"blockedScoringAtt","value":"2"},{"fh":"165","sh":"113","type":"accuratePass","value":"278"},{"fh":"11","sh":"6","type":"wonTackle","value":"17"},{"fh":"4","sh":"4","type":"lostCorners","value":"8"},{"fh":"0","sh":"1","type":"goalsConceded","value":"1"},{"fh":"3","sh":"1","type":"saves","value":"4"},{"fh":"0","sh":"2","type":"totalScoringAtt","value":"2"},{"fh":"0","sh":"2","type":"subsMade","value":"2"},{"fh":"9","sh":"13","type":"totalThrows","value":"22"},{"fh":"0","sh":"1","type":"totalYellowCard","value":"1"},{"fh":"6","sh":"3","type":"goalKicks","value":"9"},{"fh":"220","sh":"148","type":"totalPass","value":"368"},{"fh":"6","sh":"9","type":"fkFoulWon","value":"15"},{"fh":"11","sh":"11","type":"totalTackle","value":"22"},{"fh":"0","sh":"1","type":"totalOffside","value":"1"},{"fh":"5","sh":"9","type":"fkFoulLost","value":"14"},{"fh":"4","sh":"0","type":"wonCorners","value":"4"},{"fh":"44.7","sh":"33.9","type":"possessionPercentage","value":"39.7"},{"fh":"3","sh":"13","type":"totalClearance","value":"16"},{"fh":"4","sh":"0","type":"cornerTaken","value":"4"},{"type":"formationUsed","value":"433"}]}],"matchDetailsExtra":{"matchOfficial":[{"id":"c1lnlklibw1euf60h7pogl9sl","type":"Main","firstName":"Wilton","lastName":"Pereira Sampaio"},{"id":"cizyw9b1vio9mesvfs72lqn6d","type":"Lineman 1","firstName":"Bruno","lastName":"Boschilia"},{"id":"cvj1apkje3pr779tpolle0gd1","type":"Lineman 2","firstName":"Kleber Lucio","lastName":"Gil"},{"id":"2lf78nu56htp4s7fbdkblcu6t","type":"Fourth official","firstName":"Anderson","lastName":"Daronco"}]}}}